Workbook

Sheet Self-Assessment
A1: EQuiPD | B1: short_q | C1: Question | D1: Response | E1: Notes | H1: DS | I1: CB | J1: PS | K1: IM | L1: AP | M1: SE | N1: TC | O1: DI | P1: IP | Q1: PE | R1: DE | S1: SO | T1: AI
A2: v260116
C3: EQuiPD: Equity in Air Quality Policy & Data Ecosystem
C4: Self-Assessment Tool
C6: Overview
C7: The Equity in Air Quality Policy and Data Ecosystem self-assessment (EQuiPD) tool will help you understand your city’s ability to effectively manage, use, craft, and implement policies at the intersection of air quality and equity - informed by air quality, health and equity data. EQuiPD is designed to guide your development around data, air quality monitoring, technical capacity, training, and infrastructure so that you can address air quality with full consideration of health and equity. You can use EQuiPD-generated results to ensure you have the necessary data for a more complete understanding of your city and determine if you have fundamental information necessary for designing equitable air quality policies and assessing policy benefits aligned with the five equity impact areas outlined in the C40 report: Clean air, healthy and thriving communities: Opportunities for city leadership [1]. Finally, EQuiPD will guide you in identifying gaps across your city’s equity in air quality policy ecosystem so you can focus development and strengthen the underlying data resources, technical capacities to manage and process data, and partnerships for sharing and integrating air quality, health and equity data that can compliment your city’s efforts to ensure more equitable policy outcomes.
C8: [1] Clean air, healthy and thriving communities: Opportunities for city leadership
C10: How to use the self-assessment tool
C11: The EQuiPD self-assessment contains 80 questions regarding data in our city. These questions are broken down across how data is collected, linked, disaggregated and integrated, analyzed, and communicated. Your responses to these questions will be used to calculate scores across six categories within four ecosystem domains and three themes of equity (see [2] for more detail). As you make progress in developing your city's data ecosystem for equitable air quality policies, you are encouraged to redo this assessment again in the future and reflect on growth over time. **Note: Questions marked '*' are essential to answer and should not be skipped. Other questions will help add nuance for EQuiPD to understand your city's policy and data ecosystem and are highly recommended to answer.
C12: Self-scoring is necessary as you have the best knowledge of your own city’s capacities. The scoring scale for all questions is described as follows. You may assign fractional scores (e.g., 2.5) if you fall between two scores.
C13: 0 No implementation or unknown.
C14: 1 Limited implementation. Pilot work is underway related to some aspects of this question, but it is not sustainable or will not provide long-term actionable insights.
C15: 2 Partial implementation. There is operational work related to this question that is ongoing but may be limited in terms of equity integration (e.g., it has not reached marginalized neighborhoods or cannot fully quantify or address potential disparities).
C16: 3 Full implementation. Long-term, sustainable, and transparent ability to address this question. Equity is given full consideration with disaggregation (when applicable) across multiple characterizations (i.e., demographic, socioeconomic).
... C21: Self-Assessment Questions
C22: Preliminary | D22: Answers
B23: City | C23: City name? (Use dropdown list to select from C40 cities, or enter 'Not listed') | D23: United Arab Emirates - Dubai
B24: Other_city | C24: Other city (write here, formatted as "Country - City")
B25: Name | C25: Name of person filling out this self-assessment?
B26: Date | C26: Date completed | D26: 11/26/2025
B27: Share | C27: Are you willing to share your results with other C40 cities? (Yes/No) | D27: Yes
H28: Categories | N28: Domains | R28: Themes
B29: 0 | C29: Data Collection (Health, Air Quality, Demographics, Socioeconomics) | D29: Score (0-3) | E29: Notes | H29: DS | I29: CB | J29: PS | K29: IM | L29: AP | M29: SE | N29: TC | O29: DI | P29: IP | Q29: PE | R29: DE | S29: SO | T29: AI
B30: =B29+1 -> 1 | C30: *Do air pollution monitoring locations prioritize high-risk groups (for example., children, elderly, people with pre-existing conditions) and neighborhoods with historical underinvestment? | D30: 1 | L30: 1 | P30: 1 | R30: 1
B31: =B30+1 -> 2 | C31: Are community members from marginalized or vulnerable groups–or from disproportionately exposed areas of your city–engaged in decisionmaking about where to locate air pollution monitors? Marginalized community members may include low-income residents, racial or ethnic minority groups, migrants, linguistic minorities, religious minorities, Indigenous peoples, women, or any other oppressed or disenfranchised group. | D31: 1 | H31: 1 | L31: 1 | Q31: 1 | T31: 1
B32: =B31+1 -> 3 | C32: Are labor unions, worker cooperatives, and community organizations actively engaged in decisionmaking about where to locate air pollution monitors? Spatial and temporal resolution should be high enough to identify specific neighborhoods and other areas of your city that are disproportionately impacted by air pollution. | D32: 1 | H32: 1 | L32: 1 | M32: 1 | Q32: 1 | S32: 1 | T32: 1
B33: =B32+1 -> 4 | C33: *Does your city collect air pollution data at high spatial and temporal resolution, especially in areas of concern and prioritize high risk groups (e.g., children, elderly, underinvested neighborhoods)? Spatial and temporal resolution should be high enough to identify specific neighborhoods and other areas of your city that are disproportionately impacted by air pollution. | D33: 1.5 | L33: 1 | N33: 1 | R33: 1
B34: =B33+1 -> 5 | C34: *Does your city collect air pollution data from point, area, and mobile sources, including power plants, shipping lanes, transportation hubs and routes, and industrial areas? | D34: 3 | M34: 1 | N34: 1 | R34: 1 | S34: 1
B35: =B34+1 -> 6 | C35: Are smaller, un-inventoried, unconventional, hyper-local, or illegal sources of air pollution tracked by your city, preferably in consultation with vulnerable communities? Such sources may include backyard burning or unlicensed chemical use. | D35: 1 | H35: 1 | J35: 1 | M35: 1 | O35: 1 | P35: 1 | Q35: 1 | R35: 1 | S35: 1
B36: =B35+1 -> 7 | C36: *Does your city collect detailed social, demographic, and economic data about its residents and where they live? These datasets might include resident age, sex and gender, income, migration status, county of origin, racial or ethnic identity, religious affiliation, primary language spoken, education level, employment status, and occupation. They might also include area-level variables like poverty rates or joblessness rates. This data is critical to understanding the sociodemographic composition of neighborhoods and how some groups might be affected by air pollution and air quality policies more than others. | D36: 1 | H36: 1 | J36: 1 | N36: 1 | P36: 1 | S36: 1 | T36: 1
B37: =B36+1 -> 8 | C37: Does your city government have partnerships with industry, transportation, and agricultural sectors to improve emission inventories? | D37: 3 | M37: 1 | Q37: 1 | S37: 1
B38: =B37+1 -> 9 | C38: *Is data collected regarding the type of energy sources (coal, oil, gas, renewables, etc.) used by households in your city, as well as the location and number of such households? For example, do you know the location and number of households that have access to “clean energy,” which includes energy sources that produce no greenhouse gas emissions during their production or use? | D38: 1 | H38: 1 | N38: 1 | S38: 1
B39: =B38+1 -> 10 | C39: Does your city have the ability (sensors, expertise, etc) to gather indoor air quality data across diverse housing types and locations (e.g., underinvested neighborhoods, high-rise apartments)? | D39: 1 | L39: 1 | N39: 1 | T39: 1
B40: =B39+1 -> 11 | C40: Does your city collect data on indoor air quality proxy measures? “Proxy measures” include any data points that indicate potential indoor air quality problems. For example, mold complaints or mold abatement requests can indicate homes with poor indoor air quality. | D40: 0 | L40: 1 | N40: 1 | T40: 1
B41: =B40+1 -> 12 | C41: *Does your city collect or have access to real-time meteorological forecast data for your city and the surrounding areas? Meteorological data can be important both for air quality monitoring and for alerting residents to potential health hazards. Such data is particularly important for cities that experience extreme weather events. | D41: 3 | L41: 1 | N41: 1 | R41: 1
B42: =B41+1 -> 13 | C42: *Does your city collect data on accessibility that can characterize inequities for specific vulnerable populations, such as low-income or elderly populations? For this question, “accessibility” refers to whether all city residents–regardless of their physical or intellectual abilities–can interact with the information on air quality and related issues that you provide. | D42: 0 | J42: 1 | O42: 1 | T42: 1
B43: =B42+1 -> 14 | C43: *Is there data to characterize access to public clean air spaces, including by multiple transportation modes, e.g. sidewalks, roadways, public transit? | D43: 0 | J43: 1 | N43: 1 | R43: 1 | S43: 1
B44: =B43+1 -> 15 | C44: *Does your city collect health outcome data at high spatial and temporal resolution? For example, does it collect data on the number of daily visits to specific clinics or hospitals (and the causes for those visits), or the number of child absences from city schools? “High spatial resolution” means that you know the approximate location (residential address, address of medical facility, or neighborhood) of the health event. “High temporal resolution” means daily or, at a minimum, weekly counts, though yearly counts can still be helpful when modeling the impacts of air pollution policies over long periods of time. Note: this question only asks whether the city government collects this data directly. Separate questions later in the questionnaire will ask about data sharing with hospitals, ministries of health, and other groups that may have health data. | D44: 1.5 | H44: 1 | K44: 1 | N44: 1 | P44: 1 | R44: 1
B45: =B44+1 -> 16 | C45: Does your city track and make available data on competing risks to health and equity (e.g., drinking water quality, pesticide use, chemical exposures)? | D45: 1 | H45: 1 | O45: 1 | R45: 1
B46: =B45+1 -> 17 | C46: *Does your city collect labor market data (e.g., by gender, race/ethnicity, age, region, occupation) on current workforce composition, sectoral vulnerabilities related to air quality policies and energy transitions, and potential for participation in green job sectors? | D46: 1 | H46: 1 | P46: 1 | S46: 1
B47: =B46+1 -> 18 | C47: Do you collect data on how air quality-related costs (such as energy or transportation expenses) affect households and businesses? | D47: 0 | K47: 1 | N47: 1 | S47: 1 | T47: 1
B48: =B47+1 -> 19 | C48: Are members of communities that are disproportionately impacted by air pollution engaged in the design and review of data systems that monitor labor market data and other job-related outcomes? For this question, “job-related” outcomes include opportunities to participate in job retraining, job placement, and green job creation programs. This is important because air quality policies may not be equitable if they result in economic hardship for vulnerable populations. Instead, equitable air quality policies should provide benefits to vulnerable populations, including economic and job-related benefits. | D48: 0 | H48: 1 | Q48: 1 | T48: 1
B49: =B48+1 -> 20 | C49: Does your city collect data to track economic transitions related to air quality (e.g., shifts in employment, consumer prices, small business closures/openings)? | D49: 0 | K49: 1 | O49: 1 | S49: 1
B50: =B49+1 -> 21 | C50: *Does your city collect data on the combined impacts of air quality interventions on employment in economically disadvantaged communities? For example, are potential job losses or gains due to air quality interventions monitored? For this question, consider all types of “air quality interventions,”, including transitions to clean (or cleaner) energy, clean (or cleaner) transportation, clean (or cleaner) waste management systems, or any other policy or program meant to reduce air pollution. | D50: 0 | H50: 1 | N50: 1 | O50: 1 | S50: 1
B51: =B50+1 -> 22 | C51: *Does your city systematically keep track of and report data gaps (for example, missing or unavailable data) in its datasets that might disproportionately impact disadvantaged communities? For this question, “datasets” include all datasets relevant to equity analyses, such as data on health burdens, employment opportunities, economic activity, accessibility (e.g., transportation), etc. | D51: 0 | H51: 1 | J51: 1 | P51: 1 | Q51: 1 | T51: 1
B52: =B51+1 -> 23 | C52: Is there a mechanism (for example, regular meetings in neighborhoods across your city) to ensure that community-generated data and lived experiences are collected and used by city government staff for policy, resource allocation, and program design? | D52: 0 | I52: 1 | O52: 1 | P52: 1 | Q52: 1 | R52: 1 | S52: 1 | T52: 1
B53: =B52+1 -> 24 | C53: *Does your city have systems for documentation and version control for all of its datasets? | D53: 0 | H53: 1 | I53: 1 | N53: 1 | P53: 1 | R53: 1 | S53: 1 | T53: 1
B54: =B53+1 -> 25 | C54: *Do air quality modeling staff collaborate with staff maintaining air quality monitoring networks so that they can bias-correct model predictions? | D54: 2 | I54: 1 | K54: 1 | L54: 1 | P54: 1 | Q54: 1 | R54: 1
B56: =B54 -> 25 | C56: Data Partnerships and Linkages | D56: Score (0-3) | E56: Notes | H56: DS | I56: CB | J56: PS | K56: IM | L56: AP | M56: SE | N56: TC | O56: DI | P56: IP | Q56: PE | R56: DE | S56: SO | T56: AI
B57: =B56+1 -> 26 | C57: *Does your city employ staff or consultants responsible for maintaining and linking air quality, environmental, demographic, health, economic, and other datasets and data pipelines? A “data pipeline” can include computing scripts–often in Python, R, or a similar language–that can make data available for analysis and sharing. | D57: 1 | H57: 1 | I57: 1 | N57: 1 | R57: 1
B58: =B57+1 -> 27 | C58: *Has your city established data sharing partnerships between each department within your city that collects datasets that are important for analyzing the equity impacts of air quality policies? These departments in your city may include environmental and air quality departments, planning departments, health departments, transportation departments, and economic development or employment departments. Partnerships may take many forms, including regularly scheduled communication among departments, cross-department working groups, or data sharing agreements and Memorandums of Understanding. | D58: 1.5 | H58: 1 | I58: 1 | P58: 1 | T58: 1
B59: =B58+1 -> 28 | C59: *Has your city established partnerships and processes to share air quality data with relevant officials in other levels of government, including state / provincial and national levels, that affect your city? Relevant officials may include those in ministries of health, public health, environment, transportation, economic development, infrastructure, and others. | D59: 2 | H59: 1 | I59: 1 | P59: 1 | R59: 1 | T59: 1
B60: =B59+1 -> 29 | C60: *Has your city established partnerships and processes to share health and economic impact/disparities data with relevant officials in other levels of government, including state / provincial and national levels, that affect your city? Relevant officials may include those in ministries of health, public health, environment, transportation, economic development, infrastructure, and others. | D60: 1 | H60: 1 | I60: 1 | P60: 1 | R60: 1 | S60: 1 | T60: 1
B61: =B60+1 -> 30 | C61: Are satellite products linked with other air pollution monitoring data and with health and economic data (e.g., hospitalizations, asthma prevalence)? Satellite-derived air quality data can complement air quality monitoring data, particularly where monitoring data is sparse. | D61: 1.5 | K61: 1 | L61: 1 | O61: 1 | R61: 1
B62: =B61+1 -> 31 | C62: *Does your city have the capacity to link air pollution model data (versus monitor data), particularly where either regulatory or low-cost air pollution monitor data is sparse? Air pollution model data (rather than monitor-based data) are often produced by outside experts. Thus, model-based data often needs to be linked. This question asks whether your city has the capacity to link this type of data. | D62: 1.5 | L62: 1 | N62: 1 | R62: 1
B63: =B62+1 -> 32 | C63: Does the city or sponsor have access to long-term air quality monitoring data from national or state / provincial governments? By “long-term,” this question refers to data collected over several years. Ideally, this data will be at high spatial and temporal (e.g., daily) resolution as well. | D63: 2 | L63: 1 | N63: 1 | R63: 1
B64: =B63+1 -> 33 | C64: Does your city have access to historical meteorological data for your city and the surrounding areas that can be linked to other data sources? Historical data can be helpful when estimating air pollution over time. | D64: 2 | L64: 1 | N64: 1 | R64: 1
B65: =B64+1 -> 34 | C65: Can your city obtain and link data from low-cost sensors maintained by non-governmental organizations or private individuals? | D65: 2 | H65: 1 | L65: 1 | O65: 1 | R65: 1
B66: =B65+1 -> 35 | C66: Is dedicated technical support provided to community groups managing their own low-cost sensor projects to ensure data quality and sensor calibration? | D66: 1 | I66: 1 | J66: 1 | L66: 1 | N66: 1 | P66: 1 | T66: 1
B67: =B66+1 -> 36 | C67: Is your city able to link and map yearly data on instances of floods, heat waves, toxic chemical contamination, and other environmental burdens? | D67: 0 | I67: 1 | N67: 1 | R67: 1
B68: =B67+1 -> 37 | C68: *Does your city link data on housing conditions, energy use patterns, household activities and behaviors, and indoor air pollutant sources? | D68: 0 | K68: 1 | L68: 1 | O68: 1 | T68: 1
B69: =B68+1 -> 38 | C69: *Are emission and/or air quality datasets linked with workforce data (e.g., employment sectors, wages, occupational health)? | D69: 0 | L69: 1 | O69: 1 | S69: 1
B70: =B69+1 -> 39 | C70: Are multiple years of historical land use and zoning data available to link to other data sets? This type of data linkage can support air quality projections, health impact projections, and economic policy impact projections, among other topics. | D70: 1.5 | M70: 1 | N70: 1 | O70: 1 | S70: 1
B71: =B70+1 -> 40 | C71: *Does your city link source-specific emissions monitoring data to health and economic datasets? For example, traffic-related NO2 data could be linked with childhood asthma rates, or shipping sulfur data could be linked with respiratory hospitalizations. | D71: 0 | M71: 1 | O71: 1 | P71: 1 | R71: 1
B73: =B71 -> 40 | C73: Data Disaggregation and Integration | D73: Score (0-3) | E73: Notes | H73: DS | I73: CB | J73: PS | K73: IM | L73: AP | M73: SE | N73: TC | O73: DI | P73: IP | Q73: PE | R73: DE | S73: SO | T73: AI
B74: =B73+1 -> 41 | C74: *Does your city map historical data (e.g., data over many years) on environmental burdens (air pollution, heat waves, floods, chemical exposures, etc.) and social variables (including poverty rates, migration status, race / ethnicity of residents, etc.) across neighborhoods? Put differently, can you visualize on a map the number of environmental burdens each neighborhood in your city has experienced over time to understand whether and where vulnerable populations may face higher levels of total environmental burdens? Burdens may include floods, heat waves, toxic chemical contamination, and other environmental burdens? | D74: 0 | H74: 1 | K74: 1 | N74: 1 | O74: 1 | R74: 1
B75: =B74+1 -> 42 | C75: *Is your city able to disaggregate air quality data to measure how different groups in your city–and particularly vulnerable and marginalized groups–are exposed to different levels of air pollution? This process generally requires cities to be able to link and map sociodemographic and air pollution data, and to understand both (1) how air pollution differs across neighborhoods and (2) demographic characteristics of groups living in highly polluted neighborhoods. | D75: 0 | K75: 1 | L75: 1 | N75: 1 | O75: 1 | R75: 1
B76: =B75+1 -> 43 | C76: *Are you able to disaggregate all other environmental data sources–including those measuring point / source emissions, meteorology, floods, and chemical use–by sociodemographic characteristics? As in the question above related to air pollution data, this ability is central to understanding health and economic equity impacts of air pollution. | D76: 0 | K76: 1 | N76: 1 | O76: 1 | T76: 1
B77: =B76+1 -> 44 | C77: *Can your city disaggregate labor market and economic data sources--including those job creation, job loss, and other economic costs-–by sociodemographic characteristics? | D77: 0 | K77: 1 | N77: 1 | O77: 1 | S77: 1
B78: =B77+1 -> 45 | C78: *Are all health outcomes related to air pollution exposure disaggregated by demographics such as race, income, age, gender, and geography? | D78: 0 | K78: 1 | N78: 1 | O78: 1 | R78: 1
B79: =B78+1 -> 46 | C79: *Does your city disaggregate air pollution, environmental, health, and economic data by multiple demographics simultaneously? For example, some cities may disaggregate air pollution exposure by one characteristic (e.g., nativity) at a time. However, more detailed equity analyses consider the impact of intersecting facets of identity and social position. As such, they may disaggregate data based on two or more characteristics (e.g., nativity and poverty status) at the same time. In these cases, you might consider how air pollution exposure differs among, for example, low-income migrant residents, high-income migrant residents, low-income native residents, and high-income native residents. | D79: 0 | K79: 1 | N79: 1 | O79: 1 | T79: 1
B80: =B79+1 -> 47 | C80: Do models incorporate local source contributions to identify drivers of inequitable exposures using resident-collected air quality data that is integrated with official datasets? | D80: 0 | J80: 1 | L80: 1 | M80: 1 | N80: 1 | O80: 1 | P80: 1 | T80: 1
B81: =B80+1 -> 48 | C81: *Do your city’s analyses incorporate spatially and temporally aligned (i.e., “harmonized”) demographic, air quality, health, and economic outcome data? In other words, if you use demographic, air quality, health, and economic data in your analyses, were the various types of data collected during the same time period and at the same spatial scale (for example., street-level, neighborhood-level, city-level, province-level, etc.)? | D81: 0 | H81: 1 | K81: 1 | N81: 1 | O81: 1 | R81: 1
B82: =B81+1 -> 49 | C82: Are community-generated data sources and data from lived experiences integrated into official city data sources? | D82: 0 | I82: 1 | M82: 1 | O82: 1 | P82: 1 | R82: 1 | T82: 1
B84: =B82 -> 49 | C84: Data Analysis and Modeling | D84: Score (0-3) | E84: Notes | H84: DS | I84: CB | J84: PS | K84: IM | L84: AP | M84: SE | N84: TC | O84: DI | P84: IP | Q84: PE | R84: DE | S84: SO | T84: AI
B85: =B84+1 -> 50 | C85: *Does your city have access to computing resources including computers and statistical analysis software (e.g., R, SAS, or similar software, as well as GIS software) that can (1) process large-scale datasets and (2) estimate differences in air pollution risks across different population groups? It is important that these computing resources are powerful enough to handle large datasets and to estimate how health and economic outcomes are affected by air pollution (i.e., so-called “exposure-response datasets and risk models”). | D85: 1 | H85: 1 | N85: 1 | R85: 1
B86: =B85+1 -> 51 | C86: Does your city use open-source data analysis tools (e.g., R, QGIS) for its analyses? Using open-source tools can ensure your city’s technical capacity is robust because they do not require your city to purchase new software every few years. | D86: 0 | H86: 1 | I86: 1 | N86: 1 | R86: 1
B87: =B86+1 -> 52 | C87: *Does your city systematically measure the effects of air quality policies to ensure they reduce inequities in air pollution exposure and related health economic effects? For example, the AQUA tool from C40 is one tool that can be used to measure health effects, but your city may choose other tools for this purpose. | D87: 1 | J87: 1 | L87: 1 | P87: 1 | S87: 1 | T87: 1
B88: =B87+1 -> 53 | C88: *Are health risks from air pollution explicitly modeled for multiple demographics, and do these risks consider non-chemical stressors? | D88: 0 | K88: 1 | O88: 1 | R88: 1
B89: =B88+1 -> 54 | C89: Are data fusion techniques used to combine remote sensing, ground-based, and modeled data to enhance exposure assessment? | D89: 1 | L89: 1 | N89: 1 | O89: 1 | R89: 1 | S89: 1 | T89: 1
B90: =B89+1 -> 55 | C90: Are model assumptions and data limitations clearly documented and communicated? | D90: 1 | K90: 1 | P90: 1 | Q90: 1 | R90: 1
B91: =B90+1 -> 56 | C91: Are exposure models evaluated for accuracy where monitoring data may be sparse? | D91: 1 | K91: 1 | L91: 1 | N91: 1 | R91: 1
B92: =B91+1 -> 57 | C92: Are appropriate concentration–response functions available and applied? | D92: 0 | K92: 1 | O92: 1 | R92: 1
B93: =B92+1 -> 58 | C93: *Are baseline population and health outcome incidence data available? | D93: 0 | K93: 1 | O93: 1 | R93: 1
B94: =B93+1 -> 59 | C94: *Are analyses stratified by socio-demographic groups to assess whether vulnerable populations benefit equally from interventions? | D94: 0 | K94: 1 | N94: 1 | T94: 1
B95: =B94+1 -> 60 | C95: Is population-specific epidemiological literature used for equity analysis? (i.e., using research from/with affected populations) | D95: 0 | K95: 1 | Q95: 1 | R95: 1
B96: =B95+1 -> 61 | C96: *Do evaluations attempt to assess whether health and economic disparities among marginalized groups (compared to groups who are not marginalized) from air pollution and air quality policies are narrowing or widening over time? | D96: 0 | I96: 1 | O96: 1 | T96: 1
B97: =B96+1 -> 62 | C97: *Are policy-based scenarios evaluated for distributional fairness (who benefits most/least)? | D97: 0 | K97: 1 | P97: 1 | Q97: 1 | R97: 1 | S97: 1 | T97: 1
B98: =B97+1 -> 63 | C98: *Are health and equity outcomes among marginalized, vulnerable, or particularly susceptible groups (children, elderly, people with chronic illness) explicitly quantified? | D98: 0 | K98: 1 | N98: 1 | R98: 1
B99: =B98+1 -> 64 | C99: *Do health and economic impact assessments of air quality policies include analyses of differential burdens across diverse groups and local economies (e.g., low income workers)? | D99: 0 | J99: 1 | K99: 1 | N99: 1 | P99: 1 | R99: 1 | S99: 1
B100: =B99+1 -> 65 | C100: *Does your city analyze health and economic costs associated with policy compliance or adaptation and how this is distributed across communities and businesses of different sizes? | D100: 0 | J100: 1 | O100: 1 | T100: 1
B101: =B100+1 -> 66 | C101: *Does your city have programs or policies to ensure that community members from marginalized, vulnerable, or disproportionately exposed areas are engaged in decisionmaking about how to interpret and analyze air pollution data from your city? | D101: 0 | H101: 1 | Q101: 1 | T101: 1
B102: =B101+1 -> 67 | C102: Do evaluations report whether health outcomes (e.g., fewer hospital visits, lower asthma rates) improve after interventions? | D102: 0 | H102: 1 | J102: 1 | N102: 1 | Q102: 1 | R102: 1
B103: =B102+1 -> 68 | C103: Do marginalized groups or their representatives have a clear mechanism to provide input on—or object to—the data and assumptions underpinning equity impact analyses? | D103: 0 | H103: 1 | K103: 1 | Q103: 1 | R103: 1 | T103: 1
B105: =B103 -> 68 | C105: Data Communication | D105: Score (0-3) | E105: Notes | H105: DS | I105: CB | J105: PS | K105: IM | L105: AP | M105: SE | N105: TC | O105: DI | P105: IP | Q105: PE | R105: DE | S105: SO | T105: AI
B106: =B105+1 -> 69 | C106: *Can the public access your city’s air quality and emissions data for free? Public access could include internet-based tools or apps. Note: This specific question refers only to the ability of the public to access your data. It does not refer to whether the public actually uses whatever tools may exist. | D106: 1 | H106: 1 | I106: 1 | K106: 1 | M106: 1 | N106: 1 | O106: 1 | T106: 1
B107: =B106+1 -> 70 | C107: *Are public-facing data platforms designed with community input to ensure accessibility (e.g., mobile-friendly, low-data consumption, interactive maps) rather than relying solely on raw data files? | D107: 2 | J107: 1 | L107: 1 | M107: 1 | O107: 1 | Q107: 1 | T107: 1
B108: =B107+1 -> 71 | C108: *Are real-time air quality alerts and warnings, resources, and recommendations for protective actions available to residents in all neighborhoods in your city? For this question, consider whether these resources (alerts, recommendations, etc.) are disseminated through multiple platforms, including websites, apps, text messaging, or other media. | D108: 1.5 | J108: 1 | O108: 1 | T108: 1
B109: =B108+1 -> 72 | C109: Does your city track public engagement with any publicly available air quality data? This could include simply counting the number of visits to relevant webpages, and it would be a helpful datapoint to consider when building equitable air quality policies. | D109: 1.5 | H109: 1 | N109: 1 | T109: 1
B110: =B109+1 -> 73 | C110: *Are policy effects evaluated and reported back to communities in a transparent and publicly accessible way? | D110: 1 | H110: 1 | K110: 1 | Q110: 1 | T110: 1
...

Sheet Scoring
H1: CB | I1: PS | J1: IM | K1: AP | L1: SE | M1: TC | N1: DI | O1: IP | P1: PE | Q1: DE | R1: SO | S1: AI
C3: EQuiPD: Equity in Air Quality Policy & Data Ecosystem
C4: Scoring
A5: EQuiPD | B5: ="EQuiPD Self-Assessment Scores: "&IF('Self-Assessment'!$D$23="Not listed",'Self-Assessment'!$D$24,'Self-Assessment'!$D$23)&" "&'Self-Assessment'!D$26 -> EQuiPD Self-Assessment Scores: United Arab Emirates - Dubai 11/26/2025 | G5: EQuiPD
A7: EQuiPD | B7: ="EQuiPD Self-Assessment Scores: "&IF('Self-Assessment'!$D$23="Not listed",'Self-Assessment'!$D$24,'Self-Assessment'!$D$23)&" "&'Self-Assessment'!D$26 -> EQuiPD Self-Assessment Scores: United Arab Emirates - Dubai 11/26/2025 | E7: View recommendations and next steps | G7: EQuiPD
B8: Data-sharing partnerships & management tools
B9: Robust capacity in data collection, analysis, and public transparency is essential for equitable air quality policies. This means systems that detect health and economic disparities, integrate diverse datasets, and map cumulative environmental burdens by community and socioeconomic status. Open access to data, strong local partnerships, and active involvement of marginalized communities in monitoring and decision-making help ensure that interventions are both effective and just. Regular, transparent reporting and evaluation of outcomes are crucial for accountability and ongoing policy improvement.
D10: Learn more about Categories, Domains, and Themes
C11: Equity Themes
B12: Domains | C12: Distributional Equity | D12: Socioeconomic Resilience and Opportunity | E12: Access and Inclusivity | F12: Overall
B13: Technical Capacity | C13: =IFERROR(AVERAGEIFS('Self-Assessment'!D$29:D$313,'Self-Assessment'!H$29:H$313,1,'Self-Assessment'!N$29:N$313,1,'Self-Assessment'!R$29:R$313,1),"") -> 0.4375 | D13: =IFERROR(AVERAGEIFS('Self-Assessment'!D$29:D$313,'Self-Assessment'!H$29:H$313,1,'Self-Assessment'!N$29:N$313,1,'Self-Assessment'!S$29:S$313,1),"") -> 0.5 | E13: =IFERROR(AVERAGEIFS('Self-Assessment'!D$29:D$313,'Self-Assessment'!H$29:H$313,1,'Self-Assessment'!N$29:N$313,1,'Self-Assessment'!T$29:T$313,1),"") -> 0.875 | F13: =IFERROR(AVERAGEIFS('Self-Assessment'!D$29:D$313,'Self-Assessment'!H$29:H$313,1,'Self-Assessment'!N$29:N$313,1),"") -> 0.61538462
B14: Data Integration | C14: =IFERROR(AVERAGEIFS('Self-Assessment'!D$29:D$313,'Self-Assessment'!H$29:H$313,1,'Self-Assessment'!O$29:O$313,1,'Self-Assessment'!R$29:R$313,1),"") -> 0.8 | D14: =IFERROR(AVERAGEIFS('Self-Assessment'!D$29:D$313,'Self-Assessment'!H$29:H$313,1,'Self-Assessment'!O$29:O$313,1,'Self-Assessment'!S$29:S$313,1),"") -> 0.5 | E14: =IFERROR(AVERAGEIFS('Self-Assessment'!D$29:D$313,'Self-Assessment'!H$29:H$313,1,'Self-Assessment'!O$29:O$313,1,'Self-Assessment'!T$29:T$313,1),"") -> 1 | F14: =IFERROR(AVERAGEIFS('Self-Assessment'!D$29:D$313,'Self-Assessment'!H$29:H$313,1,'Self-Assessment'!O$29:O$313,1),"") -> 0.71428571
B15: Internal Processes | C15: =IFERROR(AVERAGEIFS('Self-Assessment'!D$29:D$313,'Self-Assessment'!H$29:H$313,1,'Self-Assessment'!P$29:P$313,1,'Self-Assessment'!R$29:R$313,1),"") -> 1.1 | D15: =IFERROR(AVERAGEIFS('Self-Assessment'!D$29:D$313,'Self-Assessment'!H$29:H$313,1,'Self-Assessment'!P$29:P$313,1,'Self-Assessment'!S$29:S$313,1),"") -> 0.8 | E15: =IFERROR(AVERAGEIFS('Self-Assessment'!D$29:D$313,'Self-Assessment'!H$29:H$313,1,'Self-Assessment'!P$29:P$313,1,'Self-Assessment'!T$29:T$313,1),"") -> 0.91666667 | F15: =IFERROR(AVERAGEIFS('Self-Assessment'!D$29:D$313,'Self-Assessment'!H$29:H$313,1,'Self-Assessment'!P$29:P$313,1),"") -> 1
B16: Participation and Empowerment | C16: =IFERROR(AVERAGEIFS('Self-Assessment'!D$29:D$313,'Self-Assessment'!H$29:H$313,1,'Self-Assessment'!Q$29:Q$313,1,'Self-Assessment'!R$29:R$313,1),"") -> 0.33333333 | D16: =IFERROR(AVERAGEIFS('Self-Assessment'!D$29:D$313,'Self-Assessment'!H$29:H$313,1,'Self-Assessment'!Q$29:Q$313,1,'Self-Assessment'!S$29:S$313,1),"") -> 1 | E16: =IFERROR(AVERAGEIFS('Self-Assessment'!D$29:D$313,'Self-Assessment'!H$29:H$313,1,'Self-Assessment'!Q$29:Q$313,1,'Self-Assessment'!T$29:T$313,1),"") -> 0.42857143 | F16: =IFERROR(AVERAGEIFS('Self-Assessment'!D$29:D$313,'Self-Assessment'!H$29:H$313,1,'Self-Assessment'!Q$29:Q$313,1),"") -> 0.44444444
B17: Overall | C17: =IFERROR(AVERAGEIFS('Self-Assessment'!D$29:D$313,'Self-Assessment'!H$29:H$313,1,'Self-Assessment'!R$29:R$313,1),"") -> 0.75 | D17: =IFERROR(AVERAGEIFS('Self-Assessment'!D$29:D$313,'Self-Assessment'!H$29:H$313,1,'Self-Assessment'!S$29:S$313,1),"") -> 0.75 | E17: =IFERROR(AVERAGEIFS('Self-Assessment'!D$29:D$313,'Self-Assessment'!H$29:H$313,1,'Self-Assessment'!T$29:T$313,1),"") -> 0.78571429 | F17: =IFERROR(AVERAGEIFS('Self-Assessment'!D$29:D$313,'Self-Assessment'!H$29:H$313,1),"") -> 0.75925926
B19: City/institutional buy-in, capacity building & training
B20: Building and sustaining robust technical and organizational capacity is vital for equitable air quality policy-making. This involves having political buy-in to channel resources and mandate and accessible tools and trained staff to map, analyze, and communicate air quality gradients, their health and equity impacts, as well as resources for ongoing public and community training. Budgets and leadership structures must support long-term system upgrades, prioritize high-burden communities, and ensure regular, transparent evaluations—including independent audits and mechanisms for community input. Effective capacity also requires cross-sector coordination, sustained funding, and a commitment to policies that target disparity reduction and reflect the needs and diversity of the most affected populations.
C22: Equity Themes
B23: Domains | C23: Distributional Equity | D23: Socioeconomic Resilience and Opportunity | E23: Access and Inclusivity | F23: Overall
B24: Technical Capacity | C24: =IFERROR(AVERAGEIFS('Self-Assessment'!D$29:D$313,'Self-Assessment'!I$29:I$313,1,'Self-Assessment'!N$29:N$313,1,'Self-Assessment'!R$29:R$313,1),"") -> 0.25 | D24: =IFERROR(AVERAGEIFS('Self-Assessment'!D$29:D$313,'Self-Assessment'!I$29:I$313,1,'Self-Assessment'!N$29:N$313,1,'Self-Assessment'!S$29:S$313,1),"") -> 0 | E24: =IFERROR(AVERAGEIFS('Self-Assessment'!D$29:D$313,'Self-Assessment'!I$29:I$313,1,'Self-Assessment'!N$29:N$313,1,'Self-Assessment'!T$29:T$313,1),"") -> 0.66666667 | F24: =IFERROR(AVERAGEIFS('Self-Assessment'!D$29:D$313,'Self-Assessment'!I$29:I$313,1,'Self-Assessment'!N$29:N$313,1),"") -> 0.5
B25: Data Integration | C25: =IFERROR(AVERAGEIFS('Self-Assessment'!D$29:D$313,'Self-Assessment'!I$29:I$313,1,'Self-Assessment'!O$29:O$313,1,'Self-Assessment'!R$29:R$313,1),"") -> 0 | D25: =IFERROR(AVERAGEIFS('Self-Assessment'!D$29:D$313,'Self-Assessment'!I$29:I$313,1,'Self-Assessment'!O$29:O$313,1,'Self-Assessment'!S$29:S$313,1),"") -> 0 | E25: =IFERROR(AVERAGEIFS('Self-Assessment'!D$29:D$313,'Self-Assessment'!I$29:I$313,1,'Self-Assessment'!O$29:O$313,1,'Self-Assessment'!T$29:T$313,1),"") -> 0.25 | F25: =IFERROR(AVERAGEIFS('Self-Assessment'!D$29:D$313,'Self-Assessment'!I$29:I$313,1,'Self-Assessment'!O$29:O$313,1),"") -> 0.25
B26: Internal Processes | C26: =IFERROR(AVERAGEIFS('Self-Assessment'!D$29:D$313,'Self-Assessment'!I$29:I$313,1,'Self-Assessment'!P$29:P$313,1,'Self-Assessment'!R$29:R$313,1),"") -> 0.83333333 | D26: =IFERROR(AVERAGEIFS('Self-Assessment'!D$29:D$313,'Self-Assessment'!I$29:I$313,1,'Self-Assessment'!P$29:P$313,1,'Self-Assessment'!S$29:S$313,1),"") -> 0.33333333 | E26: =IFERROR(AVERAGEIFS('Self-Assessment'!D$29:D$313,'Self-Assessment'!I$29:I$313,1,'Self-Assessment'!P$29:P$313,1,'Self-Assessment'!T$29:T$313,1),"") -> 0.78571429 | F26: =IFERROR(AVERAGEIFS('Self-Assessment'!D$29:D$313,'Self-Assessment'!I$29:I$313,1,'Self-Assessment'!P$29:P$313,1),"") -> 0.9375
B27: Participation and Empowerment | C27: =IFERROR(AVERAGEIFS('Self-Assessment'!D$29:D$313,'Self-Assessment'!I$29:I$313,1,'Self-Assessment'!Q$29:Q$313,1,'Self-Assessment'!R$29:R$313,1),"") -> 1 | D27: =IFERROR(AVERAGEIFS('Self-Assessment'!D$29:D$313,'Self-Assessment'!I$29:I$313,1,'Self-Assessment'!Q$29:Q$313,1,'Self-Assessment'!S$29:S$313,1),"") -> 0.75 | E27: =IFERROR(AVERAGEIFS('Self-Assessment'!D$29:D$313,'Self-Assessment'!I$29:I$313,1,'Self-Assessment'!Q$29:Q$313,1,'Self-Assessment'!T$29:T$313,1),"") -> 0.25 | F27: =IFERROR(AVERAGEIFS('Self-Assessment'!D$29:D$313,'Self-Assessment'!I$29:I$313,1,'Self-Assessment'!Q$29:Q$313,1),"") -> 0.75
B28: Overall | C28: =IFERROR(AVERAGEIFS('Self-Assessment'!D$29:D$313,'Self-Assessment'!I$29:I$313,1,'Self-Assessment'!R$29:R$313,1),"") -> 0.66666667 | D28: =IFERROR(AVERAGEIFS('Self-Assessment'!D$29:D$313,'Self-Assessment'!I$29:I$313,1,'Self-Assessment'!S$29:S$313,1),"") -> 0.625 | E28: =IFERROR(AVERAGEIFS('Self-Assessment'!D$29:D$313,'Self-Assessment'!I$29:I$313,1,'Self-Assessment'!T$29:T$313,1),"") -> 0.625 | F28: =IFERROR(AVERAGEIFS('Self-Assessment'!D$29:D$313,'Self-Assessment'!I$29:I$313,1),"") -> 0.70588235
B30: ="EQuiPD Self-Assessment Scores: "&IF('Self-Assessment'!$D$23="Not listed",'Self-Assessment'!$D$24,'Self-Assessment'!$D$23)&" "&'Self-Assessment'!D$26 -> EQuiPD Self-Assessment Scores: United Arab Emirates - Dubai 11/26/2025
B31: Public support & engagement
B32: Ensuring that air quality policy-making addresses the diverse needs of all communities, especially the most vulnerable is critical to building public support & engagement. This means collecting and sharing data on access to clean air spaces, transportation, and public warnings, while tailoring resources and risk communications in multiple formats and languages. Economic impact assessments and compliance costs should explicitly analyze and address differential burdens, and feedback mechanisms must enable meaningful input from marginalized groups. Accessible and inclusive information about air pollution, impacts from policies and live tracking of changes over team can be game changing when it comes to building public support and addressing backlash. Sustained training, participatory processes, and investments in clean air monitoring infrastructure—combined with regular evaluation of health outcomes, public accountability, and integration of citizen data—ensure that policies are both effective and equitable for populations such as low-income, elderly, Indigenous, and minority residents.
C34: Equity Themes
B35: Domains | C35: Distributional Equity | D35: Socioeconomic Resilience and Opportunity | E35: Access and Inclusivity | F35: Overall
B36: Technical Capacity | C36: =IFERROR(AVERAGEIFS('Self-Assessment'!D$29:D$313,'Self-Assessment'!J$29:J$313,1,'Self-Assessment'!N$29:N$313,1,'Self-Assessment'!R$29:R$313,1),"") -> 0 | D36: =IFERROR(AVERAGEIFS('Self-Assessment'!D$29:D$313,'Self-Assessment'!J$29:J$313,1,'Self-Assessment'!N$29:N$313,1,'Self-Assessment'!S$29:S$313,1),"") -> 0.33333333 | E36: =IFERROR(AVERAGEIFS('Self-Assessment'!D$29:D$313,'Self-Assessment'!J$29:J$313,1,'Self-Assessment'!N$29:N$313,1,'Self-Assessment'!T$29:T$313,1),"") -> 0.66666667 | F36: =IFERROR(AVERAGEIFS('Self-Assessment'!D$29:D$313,'Self-Assessment'!J$29:J$313,1,'Self-Assessment'!N$29:N$313,1),"") -> 0.33333333
B37: Data Integration | C37: =IFERROR(AVERAGEIFS('Self-Assessment'!D$29:D$313,'Self-Assessment'!J$29:J$313,1,'Self-Assessment'!O$29:O$313,1,'Self-Assessment'!R$29:R$313,1),"") -> 1 | D37: =IFERROR(AVERAGEIFS('Self-Assessment'!D$29:D$313,'Self-Assessment'!J$29:J$313,1,'Self-Assessment'!O$29:O$313,1,'Self-Assessment'!S$29:S$313,1),"") -> 1 | E37: =IFERROR(AVERAGEIFS('Self-Assessment'!D$29:D$313,'Self-Assessment'!J$29:J$313,1,'Self-Assessment'!O$29:O$313,1,'Self-Assessment'!T$29:T$313,1),"") -> 0.7 | F37: =IFERROR(AVERAGEIFS('Self-Assessment'!D$29:D$313,'Self-Assessment'!J$29:J$313,1,'Self-Assessment'!O$29:O$313,1),"") -> 0.75
B38: Internal Processes | C38: =IFERROR(AVERAGEIFS('Self-Assessment'!D$29:D$313,'Self-Assessment'!J$29:J$313,1,'Self-Assessment'!P$29:P$313,1,'Self-Assessment'!R$29:R$313,1),"") -> 0.5 | D38: =IFERROR(AVERAGEIFS('Self-Assessment'!D$29:D$313,'Self-Assessment'!J$29:J$313,1,'Self-Assessment'!P$29:P$313,1,'Self-Assessment'!S$29:S$313,1),"") -> 0.75 | E38: =IFERROR(AVERAGEIFS('Self-Assessment'!D$29:D$313,'Self-Assessment'!J$29:J$313,1,'Self-Assessment'!P$29:P$313,1,'Self-Assessment'!T$29:T$313,1),"") -> 0.6 | F38: =IFERROR(AVERAGEIFS('Self-Assessment'!D$29:D$313,'Self-Assessment'!J$29:J$313,1,'Self-Assessment'!P$29:P$313,1),"") -> 0.57142857
B39: Participation and Empowerment | C39: =IFERROR(AVERAGEIFS('Self-Assessment'!D$29:D$313,'Self-Assessment'!J$29:J$313,1,'Self-Assessment'!Q$29:Q$313,1,'Self-Assessment'!R$29:R$313,1),"") -> 0.33333333 | D39: =IFERROR(AVERAGEIFS('Self-Assessment'!D$29:D$313,'Self-Assessment'!J$29:J$313,1,'Self-Assessment'!Q$29:Q$313,1,'Self-Assessment'!S$29:S$313,1),"") -> 1 | E39: =IFERROR(AVERAGEIFS('Self-Assessment'!D$29:D$313,'Self-Assessment'!J$29:J$313,1,'Self-Assessment'!Q$29:Q$313,1,'Self-Assessment'!T$29:T$313,1),"") -> 1 | F39: =IFERROR(AVERAGEIFS('Self-Assessment'!D$29:D$313,'Self-Assessment'!J$29:J$313,1,'Self-Assessment'!Q$29:Q$313,1),"") -> 0.6
B40: Overall | C40: =IFERROR(AVERAGEIFS('Self-Assessment'!D$29:D$313,'Self-Assessment'!J$29:J$313,1,'Self-Assessment'!R$29:R$313,1),"") -> 0.2 | D40: =IFERROR(AVERAGEIFS('Self-Assessment'!D$29:D$313,'Self-Assessment'!J$29:J$313,1,'Self-Assessment'!S$29:S$313,1),"") -> 0.6 | E40: =IFERROR(AVERAGEIFS('Self-Assessment'!D$29:D$313,'Self-Assessment'!J$29:J$313,1,'Self-Assessment'!T$29:T$313,1),"") -> 0.72222222 | F40: =IFERROR(AVERAGEIFS('Self-Assessment'!D$29:D$313,'Self-Assessment'!J$29:J$313,1),"") -> 0.53571429
B42: Health & economic impact modelling
B43: Equitable air quality policy-making relies on comprehensive, accurate modeling and monitoring systems that explicitly quantify health and economic impacts of particular policies for vulnerable and marginalized groups. This involves ensuring exposure and scenario-based models reflect real-world conditions through collaboration with monitoring networks, validation in data-sparse areas, and integration of fine-scale demographic and economic data. Analyses must be stratified by factors such as income, age, race, and geography, translating results into meaningful, accessible formats (e.g., public dashboards, maps, and plain-language summaries) that inform both policy and community resilience efforts. Ongoing community input, transparent communication of methods and limitations, and regular updates ensure that modeling truly supports fair distribution of benefits and burdens, strengthens preparedness, and provides targeted support to those most affected by air pollution and regulatory changes.
C45: Equity Themes
B46: Domains | C46: Distributional Equity | D46: Socioeconomic Resilience and Opportunity | E46: Access and Inclusivity | F46: Overall
B47: Technical Capacity | C47: =IFERROR(AVERAGEIFS('Self-Assessment'!D$29:D$313,'Self-Assessment'!K$29:K$313,1,'Self-Assessment'!N$29:N$313,1,'Self-Assessment'!R$29:R$313,1),"") -> 0.3125 | D47: =IFERROR(AVERAGEIFS('Self-Assessment'!D$29:D$313,'Self-Assessment'!K$29:K$313,1,'Self-Assessment'!N$29:N$313,1,'Self-Assessment'!S$29:S$313,1),"") -> 0 | E47: =IFERROR(AVERAGEIFS('Self-Assessment'!D$29:D$313,'Self-Assessment'!K$29:K$313,1,'Self-Assessment'!N$29:N$313,1,'Self-Assessment'!T$29:T$313,1),"") -> 0.2 | F47: =IFERROR(AVERAGEIFS('Self-Assessment'!D$29:D$313,'Self-Assessment'!K$29:K$313,1,'Self-Assessment'!N$29:N$313,1),"") -> 0.25
B48: Data Integration | C48: =IFERROR(AVERAGEIFS('Self-Assessment'!D$29:D$313,'Self-Assessment'!K$29:K$313,1,'Self-Assessment'!O$29:O$313,1,'Self-Assessment'!R$29:R$313,1),"") -> 0.1875 | D48: =IFERROR(AVERAGEIFS('Self-Assessment'!D$29:D$313,'Self-Assessment'!K$29:K$313,1,'Self-Assessment'!O$29:O$313,1,'Self-Assessment'!S$29:S$313,1),"") -> 0 | E48: =IFERROR(AVERAGEIFS('Self-Assessment'!D$29:D$313,'Self-Assessment'!K$29:K$313,1,'Self-Assessment'!O$29:O$313,1,'Self-Assessment'!T$29:T$313,1),"") -> 0.25 | F48: =IFERROR(AVERAGEIFS('Self-Assessment'!D$29:D$313,'Self-Assessment'!K$29:K$313,1,'Self-Assessment'!O$29:O$313,1),"") -> 0.17857143
B49: Internal Processes | C49: =IFERROR(AVERAGEIFS('Self-Assessment'!D$29:D$313,'Self-Assessment'!K$29:K$313,1,'Self-Assessment'!P$29:P$313,1,'Self-Assessment'!R$29:R$313,1),"") -> 0.9 | D49: =IFERROR(AVERAGEIFS('Self-Assessment'!D$29:D$313,'Self-Assessment'!K$29:K$313,1,'Self-Assessment'!P$29:P$313,1,'Self-Assessment'!S$29:S$313,1),"") -> 0 | E49: =IFERROR(AVERAGEIFS('Self-Assessment'!D$29:D$313,'Self-Assessment'!K$29:K$313,1,'Self-Assessment'!P$29:P$313,1,'Self-Assessment'!T$29:T$313,1),"") -> 0 | F49: =IFERROR(AVERAGEIFS('Self-Assessment'!D$29:D$313,'Self-Assessment'!K$29:K$313,1,'Self-Assessment'!P$29:P$313,1),"") -> 0.9
B50: Participation and Empowerment | C50: =IFERROR(AVERAGEIFS('Self-Assessment'!D$29:D$313,'Self-Assessment'!K$29:K$313,1,'Self-Assessment'!Q$29:Q$313,1,'Self-Assessment'!R$29:R$313,1),"") -> 0.6 | D50: =IFERROR(AVERAGEIFS('Self-Assessment'!D$29:D$313,'Self-Assessment'!K$29:K$313,1,'Self-Assessment'!Q$29:Q$313,1,'Self-Assessment'!S$29:S$313,1),"") -> 0 | E50: =IFERROR(AVERAGEIFS('Self-Assessment'!D$29:D$313,'Self-Assessment'!K$29:K$313,1,'Self-Assessment'!Q$29:Q$313,1,'Self-Assessment'!T$29:T$313,1),"") -> 0.33333333 | F50: =IFERROR(AVERAGEIFS('Self-Assessment'!D$29:D$313,'Self-Assessment'!K$29:K$313,1,'Self-Assessment'!Q$29:Q$313,1),"") -> 0.66666667
B51: Overall | C51: =IFERROR(AVERAGEIFS('Self-Assessment'!D$29:D$313,'Self-Assessment'!K$29:K$313,1,'Self-Assessment'!R$29:R$313,1),"") -> 0.41176471 | D51: =IFERROR(AVERAGEIFS('Self-Assessment'!D$29:D$313,'Self-Assessment'!K$29:K$313,1,'Self-Assessment'!S$29:S$313,1),"") -> 0 | E51: =IFERROR(AVERAGEIFS('Self-Assessment'!D$29:D$313,'Self-Assessment'!K$29:K$313,1,'Self-Assessment'!T$29:T$313,1),"") -> 0.22222222 | F51: =IFERROR(AVERAGEIFS('Self-Assessment'!D$29:D$313,'Self-Assessment'!K$29:K$313,1),"") -> 0.34615385
B53: ="EQuiPD Self-Assessment Scores: "&IF('Self-Assessment'!$D$23="Not listed",'Self-Assessment'!$D$24,'Self-Assessment'!$D$23)&" "&'Self-Assessment'!D$26 -> EQuiPD Self-Assessment Scores: United Arab Emirates - Dubai 11/26/2025
B54: Estimating air pollution
B55: Ensuring equitable air quality policy-making demands comprehensive monitoring and modeling systems that achieve high spatial and temporal coverage (especially in historically underserved neighborhoods) and prioritize addressing impacts to vulnerable groups such as children and the elderly. This includes integrating data from diverse sources (e.g., reference monitors, low-cost sensors, models, satellite data, and meteorological stations) into accessible, central repositories and using analytical tools to assess how air quality, health, employment, and energy costs vary across communities. Collaboration among city staff, technical experts, and community partners in siting, operating, and interpreting monitors and models is essential for accurate, quality-assured data that drives action. Making all monitoring and modeling outputs user-friendly and publicly accessible, while linking environmental, health, workforce, and housing data, enables targeted interventions and supports transparency, accountability, and more equitable outcomes.
C57: Equity Themes
B58: Domains | C58: Distributional Equity | D58: Socioeconomic Resilience and Opportunity | E58: Access and Inclusivity | F58: Overall
B59: Technical Capacity | C59: =IFERROR(AVERAGEIFS('Self-Assessment'!D$29:D$313,'Self-Assessment'!L$29:L$313,1,'Self-Assessment'!N$29:N$313,1,'Self-Assessment'!R$29:R$313,1),"") -> 1.5 | D59: =IFERROR(AVERAGEIFS('Self-Assessment'!D$29:D$313,'Self-Assessment'!L$29:L$313,1,'Self-Assessment'!N$29:N$313,1,'Self-Assessment'!S$29:S$313,1),"") -> 1 | E59: =IFERROR(AVERAGEIFS('Self-Assessment'!D$29:D$313,'Self-Assessment'!L$29:L$313,1,'Self-Assessment'!N$29:N$313,1,'Self-Assessment'!T$29:T$313,1),"") -> 0.6 | F59: =IFERROR(AVERAGEIFS('Self-Assessment'!D$29:D$313,'Self-Assessment'!L$29:L$313,1,'Self-Assessment'!N$29:N$313,1),"") -> 1.1666667
B60: Data Integration | C60: =IFERROR(AVERAGEIFS('Self-Assessment'!D$29:D$313,'Self-Assessment'!L$29:L$313,1,'Self-Assessment'!O$29:O$313,1,'Self-Assessment'!R$29:R$313,1),"") -> 1.125 | D60: =IFERROR(AVERAGEIFS('Self-Assessment'!D$29:D$313,'Self-Assessment'!L$29:L$313,1,'Self-Assessment'!O$29:O$313,1,'Self-Assessment'!S$29:S$313,1),"") -> 0.5 | E60: =IFERROR(AVERAGEIFS('Self-Assessment'!D$29:D$313,'Self-Assessment'!L$29:L$313,1,'Self-Assessment'!O$29:O$313,1,'Self-Assessment'!T$29:T$313,1),"") -> 0.8 | F60: =IFERROR(AVERAGEIFS('Self-Assessment'!D$29:D$313,'Self-Assessment'!L$29:L$313,1,'Self-Assessment'!O$29:O$313,1),"") -> 0.83333333
B61: Internal Processes | C61: =IFERROR(AVERAGEIFS('Self-Assessment'!D$29:D$313,'Self-Assessment'!L$29:L$313,1,'Self-Assessment'!P$29:P$313,1,'Self-Assessment'!R$29:R$313,1),"") -> 1.5 | D61: =IFERROR(AVERAGEIFS('Self-Assessment'!D$29:D$313,'Self-Assessment'!L$29:L$313,1,'Self-Assessment'!P$29:P$313,1,'Self-Assessment'!S$29:S$313,1),"") -> 1 | E61: =IFERROR(AVERAGEIFS('Self-Assessment'!D$29:D$313,'Self-Assessment'!L$29:L$313,1,'Self-Assessment'!P$29:P$313,1,'Self-Assessment'!T$29:T$313,1),"") -> 0.75 | F61: =IFERROR(AVERAGEIFS('Self-Assessment'!D$29:D$313,'Self-Assessment'!L$29:L$313,1,'Self-Assessment'!P$29:P$313,1),"") -> 1
B62: Participation and Empowerment | C62: =IFERROR(AVERAGEIFS('Self-Assessment'!D$29:D$313,'Self-Assessment'!L$29:L$313,1,'Self-Assessment'!Q$29:Q$313,1,'Self-Assessment'!R$29:R$313,1),"") -> 2 | D62: =IFERROR(AVERAGEIFS('Self-Assessment'!D$29:D$313,'Self-Assessment'!L$29:L$313,1,'Self-Assessment'!Q$29:Q$313,1,'Self-Assessment'!S$29:S$313,1),"") -> 1 | E62: =IFERROR(AVERAGEIFS('Self-Assessment'!D$29:D$313,'Self-Assessment'!L$29:L$313,1,'Self-Assessment'!Q$29:Q$313,1,'Self-Assessment'!T$29:T$313,1),"") -> 1 | F62: =IFERROR(AVERAGEIFS('Self-Assessment'!D$29:D$313,'Self-Assessment'!L$29:L$313,1,'Self-Assessment'!Q$29:Q$313,1),"") -> 1.2
B63: Overall | C63: =IFERROR(AVERAGEIFS('Self-Assessment'!D$29:D$313,'Self-Assessment'!L$29:L$313,1,'Self-Assessment'!R$29:R$313,1),"") -> 1.5416667 | D63: =IFERROR(AVERAGEIFS('Self-Assessment'!D$29:D$313,'Self-Assessment'!L$29:L$313,1,'Self-Assessment'!S$29:S$313,1),"") -> 0.75 | E63: =IFERROR(AVERAGEIFS('Self-Assessment'!D$29:D$313,'Self-Assessment'!L$29:L$313,1,'Self-Assessment'!T$29:T$313,1),"") -> 0.75 | F63: =IFERROR(AVERAGEIFS('Self-Assessment'!D$29:D$313,'Self-Assessment'!L$29:L$313,1),"") -> 1.1041667
B65: Source & emission inventories
B66: Equitable air quality policy-making requires systematic monitoring and evaluation of emissions, land use, and zoning decisions with a strong focus on communities facing the greatest risks, such as low-income and minority neighborhoods near industrial sites. Maintaining and openly sharing data on point, area, and mobile emission sources—alongside vehicle inspection programs, fenceline monitoring, and accessible records of land use changes—ensures transparency and helps link environmental and economic impacts to public health outcomes. Incorporating input from disproportionately exposed groups, workers, and community organizations into emission assessments, zoning, and policy review enables more just and inclusive decisions. Partnerships across government, industry, and labor, along with accessible platforms for data, green jobs, and retraining opportunities, support ongoing improvements, accountability, and equitable transitions, particularly for those most affected by pollution and economic changes.
C68: Equity Themes
B69: Domains | C69: Distributional Equity | D69: Socioeconomic Resilience and Opportunity | E69: Access and Inclusivity | F69: Overall
B70: Technical Capacity | C70: =IFERROR(AVERAGEIFS('Self-Assessment'!D$29:D$313,'Self-Assessment'!M$29:M$313,1,'Self-Assessment'!N$29:N$313,1,'Self-Assessment'!R$29:R$313,1),"") -> 3 | D70: =IFERROR(AVERAGEIFS('Self-Assessment'!D$29:D$313,'Self-Assessment'!M$29:M$313,1,'Self-Assessment'!N$29:N$313,1,'Self-Assessment'!S$29:S$313,1),"") -> 2.25 | E70: =IFERROR(AVERAGEIFS('Self-Assessment'!D$29:D$313,'Self-Assessment'!M$29:M$313,1,'Self-Assessment'!N$29:N$313,1,'Self-Assessment'!T$29:T$313,1),"") -> 0.5 | F70: =IFERROR(AVERAGEIFS('Self-Assessment'!D$29:D$313,'Self-Assessment'!M$29:M$313,1,'Self-Assessment'!N$29:N$313,1),"") -> 1.375
B71: Data Integration | C71: =IFERROR(AVERAGEIFS('Self-Assessment'!D$29:D$313,'Self-Assessment'!M$29:M$313,1,'Self-Assessment'!O$29:O$313,1,'Self-Assessment'!R$29:R$313,1),"") -> 0.33333333 | D71: =IFERROR(AVERAGEIFS('Self-Assessment'!D$29:D$313,'Self-Assessment'!M$29:M$313,1,'Self-Assessment'!O$29:O$313,1,'Self-Assessment'!S$29:S$313,1),"") -> 1.25 | E71: =IFERROR(AVERAGEIFS('Self-Assessment'!D$29:D$313,'Self-Assessment'!M$29:M$313,1,'Self-Assessment'!O$29:O$313,1,'Self-Assessment'!T$29:T$313,1),"") -> 0.75 | F71: =IFERROR(AVERAGEIFS('Self-Assessment'!D$29:D$313,'Self-Assessment'!M$29:M$313,1,'Self-Assessment'!O$29:O$313,1),"") -> 0.78571429
B72: Internal Processes | C72: =IFERROR(AVERAGEIFS('Self-Assessment'!D$29:D$313,'Self-Assessment'!M$29:M$313,1,'Self-Assessment'!P$29:P$313,1,'Self-Assessment'!R$29:R$313,1),"") -> 0.33333333 | D72: =IFERROR(AVERAGEIFS('Self-Assessment'!D$29:D$313,'Self-Assessment'!M$29:M$313,1,'Self-Assessment'!P$29:P$313,1,'Self-Assessment'!S$29:S$313,1),"") -> 1 | E72: =IFERROR(AVERAGEIFS('Self-Assessment'!D$29:D$313,'Self-Assessment'!M$29:M$313,1,'Self-Assessment'!P$29:P$313,1,'Self-Assessment'!T$29:T$313,1),"") -> 0 | F72: =IFERROR(AVERAGEIFS('Self-Assessment'!D$29:D$313,'Self-Assessment'!M$29:M$313,1,'Self-Assessment'!P$29:P$313,1),"") -> 0.25
B73: Participation and Empowerment | C73: =IFERROR(AVERAGEIFS('Self-Assessment'!D$29:D$313,'Self-Assessment'!M$29:M$313,1,'Self-Assessment'!Q$29:Q$313,1,'Self-Assessment'!R$29:R$313,1),"") -> 1 | D73: =IFERROR(AVERAGEIFS('Self-Assessment'!D$29:D$313,'Self-Assessment'!M$29:M$313,1,'Self-Assessment'!Q$29:Q$313,1,'Self-Assessment'!S$29:S$313,1),"") -> 1.6666667 | E73: =IFERROR(AVERAGEIFS('Self-Assessment'!D$29:D$313,'Self-Assessment'!M$29:M$313,1,'Self-Assessment'!Q$29:Q$313,1,'Self-Assessment'!T$29:T$313,1),"") -> 1.5 | F73: =IFERROR(AVERAGEIFS('Self-Assessment'!D$29:D$313,'Self-Assessment'!M$29:M$313,1,'Self-Assessment'!Q$29:Q$313,1),"") -> 1.75
B74: Overall | C74: =IFERROR(AVERAGEIFS('Self-Assessment'!D$29:D$313,'Self-Assessment'!M$29:M$313,1,'Self-Assessment'!R$29:R$313,1),"") -> 1 | D74: =IFERROR(AVERAGEIFS('Self-Assessment'!D$29:D$313,'Self-Assessment'!M$29:M$313,1,'Self-Assessment'!S$29:S$313,1),"") -> 1.9 | E74: =IFERROR(AVERAGEIFS('Self-Assessment'!D$29:D$313,'Self-Assessment'!M$29:M$313,1,'Self-Assessment'!T$29:T$313,1),"") -> 0.8 | F74: =IFERROR(AVERAGEIFS('Self-Assessment'!D$29:D$313,'Self-Assessment'!M$29:M$313,1),"") -> 1.25

Sheet Recommendations
A1: EQuiPD | B1: short_q | C1: Question | D1: Response | E1: Recommendations
A2: v112025
C3: EQuiPD: Equity in Air Quality Policy & Data Ecosystem
C4: Recommendations
C5: Recommendations
C6: To identify gaps and recommendations begin by filtering by category, domain, and/or equity theme. Use the dropdown arrows in the right-hand columns below and check '1' for the areas you are interested in learning more about. | H6: Categories | N6: Domains | R6: Themes
B7: 0 | C7: Data Collection | D7: Score | E7: Recommendations | H7: Data-sharing partnerships & management tools | I7: City/institutional buy-in, capacity building & training | J7: Public support & engagement | K7: Health & economic impact modeling | L7: Estimating air pollution | M7: Source & emission inventories | N7: Technical Capability | O7: Data Integration | P7: Internal processes | Q7: Participation and Empowerment | R7: Distributional Equity | S7: Socioeconomic Resilience and Opportunity | T7: Access and Inclusivity
B8: =B7+1 -> 1 | C8: *Do air pollution monitoring locations prioritize high-risk groups (for example., children, elderly, people with pre-existing conditions) and neighborhoods with historical underinvestment? | D8: ='Self-Assessment'!D30 -> 1 | E8: Develop a structured siting protocol that evaluates sensitive populations, land use, and pollution sources to ensure monitors are placed where health, social, economic inequities are highest. Examples: Install monitors near schools located by major roadways; add sensors in neighborhoods with high asthma hospitalization rates or high rates of joblessness or poverty. | L8: 1 | P8: 1 | R8: 1
B9: =B8+1 -> 2 | C9: Are community members from marginalized or vulnerable groups–or from disproportionately exposed areas of your city–engaged in decisionmaking about where to locate air pollution monitors? Marginalized community members may include low-income residents, racial or ethnic minority groups, migrants, linguistic minorities, religious minorities, Indigenous peoples, women, or any other oppressed or disenfranchised group. | D9: ='Self-Assessment'!D31 -> 1 | E9: Create a community advisory panel with real decision‑making power in monitor placement to ensure lived experience shapes data coverage. Examples: Allow residents to vote on final monitor placements in two high‑pollution corridors; rotate panel membership annually to include renters from impacted zones. | H9: 1 | L9: 1 | Q9: 1 | T9: 1
B10: =B9+1 -> 3 | C10: Are labor unions, worker cooperatives, and community organizations actively engaged in decisionmaking about where to locate air pollution monitors? Spatial and temporal resolution should be high enough to identify specific neighborhoods and other areas of your city that are disproportionately impacted by air pollution. | D10: ='Self-Assessment'!D32 -> 1 | E10: Include unions and community groups in siting workshops so occupational and local knowledge informs placement. Examples: Hold sessions with custodial worker unions to map indoor/outdoor hotspots; invite public housing tenant groups to identify overlooked pollution areas. | H10: 1 | L10: 1 | M10: 1 | Q10: 1 | S10: 1 | T10: 1
B11: =B10+1 -> 4 | C11: *Does your city collect air pollution data at high spatial and temporal resolution, especially in areas of concern and prioritize high risk groups (e.g., children, elderly, underinvested neighborhoods)? Spatial and temporal resolution should be high enough to identify specific neighborhoods and other areas of your city that are disproportionately impacted by air pollution. | D11: ='Self-Assessment'!D33 -> 1.5 | E11: Deploy more sensors in environmental justice neighborhoods where pollution varies block‑to‑block. Examples: Install sensors along heavy truck freight routes; add outdoor sensors around senior housing complexes affected by idling buses. | L11: 1 | N11: 1 | R11: 1
B12: =B11+1 -> 5 | C12: *Does your city collect air pollution data from point, area, and mobile sources, including power plants, shipping lanes, transportation hubs and routes, and industrial areas? | D12: ='Self-Assessment'!D34 -> 3 | E12: Integrate all major emissions inventories, including industrial, commercial, and mobile sources, into a unified city emissions tracking database. Examples: Merge port cargo handling equipment emissions with truck movement data; integrate airport ground operations emissions into citywide inventory. | M12: 1 | N12: 1 | R12: 1 | S12: 1
B13: =B12+1 -> 6 | C13: Are smaller, un-inventoried, unconventional, hyper-local, or illegal sources of air pollution tracked by your city, preferably in consultation with vulnerable communities? Such sources may include backyard burning or unlicensed chemical use. | D13: ='Self-Assessment'!D35 -> 1 | E13: Set up a reporting system where city residents can submit reports of emissions from small and unconventional sources that are often missed in inventories. Examples: Register generators used by food trucks; log emissions from small auto‑body shops using solvent‑based paints. | H13: 1 | J13: 1 | M13: 1 | O13: 1 | P13: 1 | Q13: 1 | R13: 1 | S13: 1
B14: =B13+1 -> 7 | C14: *Does your city collect detailed social, demographic, and economic data about its residents and where they live? These datasets might include resident age, sex and gender, income, migration status, county of origin, racial or ethnic identity, religious affiliation, primary language spoken, education level, employment status, and occupation. They might also include area-level variables like poverty rates or joblessness rates. This data is critical to understanding the sociodemographic composition of neighborhoods and how some groups might be affected by air pollution and air quality policies more than others. | D14: ='Self-Assessment'!D36 -> 1 | E14: Develop neighborhood- or block‑level demographic datasets to support granular equity analyses and pollutant‑exposure comparisons. Examples: Map block‑level renter density; compile household‑income distributions at sub‑neighborhood scales. | H14: 1 | J14: 1 | N14: 1 | P14: 1 | S14: 1 | T14: 1
B15: =B14+1 -> 8 | C15: Does your city government have partnerships with industry, transportation, and agricultural sectors to improve emission inventories? | D15: ='Self-Assessment'!D37 -> 3 | E15: Convene an emissions‑improvement working group with major sectors to update inventories annually. Examples: Meet quarterly with refinery operators to review flaring data; coordinate with warehouse operators to track truck fleet turnover. | M15: 1 | Q15: 1 | S15: 1
B16: =B15+1 -> 9 | C16: *Is data collected regarding the type of energy sources (coal, oil, gas, renewables, etc.) used by households in your city, as well as the location and number of such households? For example, do you know the location and number of households that have access to “clean energy,” which includes energy sources that produce no greenhouse gas emissions during their production or use? | D16: ='Self-Assessment'!D38 -> 1 | E16: Gather or estimate household fuel‑use patterns to identify indoor and outdoor emissions sources. Examples: Map homes still using wood stoves; identify multifamily buildings heated with older oil boilers. | H16: 1 | N16: 1 | S16: 1
B17: =B16+1 -> 10 | C17: Does your city have the ability (sensors, expertise, etc) to gather indoor air quality data across diverse housing types and locations (e.g., underinvested neighborhoods, high-rise apartments)? | D17: ='Self-Assessment'!D39 -> 1 | E17: Deploy portable indoor air sensors with partners such as housing authorities to understand indoor exposures. Examples: Place sensors in public‑housing units during winter heating season; monitor indoor PM2.5 in childcare centers near freeways. | L17: 1 | N17: 1 | T17: 1
B18: =B17+1 -> 11 | C18: Does your city collect data on indoor air quality proxy measures? “Proxy measures” include any data points that indicate potential indoor air quality problems. For example, mold complaints or mold abatement requests can indicate homes with poor indoor air quality. | D18: ='Self-Assessment'!D40 -> 0 | E18: Incorporate housing complaints and code enforcement requests as indicators of indoor air quality issues. Examples: Flag ventilation failure complaints; track mold reports as indicators of moisture‑driven air quality concerns. | L18: 1 | N18: 1 | T18: 1
B19: =B18+1 -> 12 | C19: *Does your city collect or have access to real-time meteorological forecast data for your city and the surrounding areas? Meteorological data can be important both for air quality monitoring and for alerting residents to potential health hazards. Such data is particularly important for cities that experience extreme weather events. | D19: ='Self-Assessment'!D41 -> 3 | E19: Integrate real‑time meteorological forecasts with pollution modeling for better short‑term predictions. Examples: Ingest hourly wind direction forecasts to predict smoke movement; apply inversion forecast data during winter stagnation periods; or simply record air temperature highs and lows alongside air quality data. | L19: 1 | N19: 1 | R19: 1
B20: =B19+1 -> 13 | C20: *Does your city collect data on accessibility that can characterize inequities for specific vulnerable populations, such as low-income or elderly populations? For this question, “accessibility” refers to whether all city residents–regardless of their physical or intellectual abilities–can interact with the information on air quality and related issues that you provide. | D20: ='Self-Assessment'!D42 -> 0 | E20: Conduct accessibility audits and study barriers that limit public access to air quality information. Examples: Survey speakers of non-native languages about website usability; analyze whether mobile users can navigate the dashboard easily. | J20: 1 | O20: 1 | T20: 1
B21: =B20+1 -> 14 | C21: *Is there data to characterize access to public clean air spaces, including by multiple transportation modes, e.g. sidewalks, roadways, public transit? | D21: ='Self-Assessment'!D43 -> 0 | E21: Map clean‑air shelters and measure their accessibility by transit and walking. Examples: Identify libraries with HEPA filtration; evaluate whether shelters near industrial zones have transit service after 20:00 (8:00pm). | J21: 1 | N21: 1 | R21: 1 | S21: 1
B22: =B21+1 -> 15 | C22: *Does your city collect health outcome data at high spatial and temporal resolution? For example, does it collect data on the number of daily visits to specific clinics or hospitals (and the causes for those visits), or the number of child absences from city schools? “High spatial resolution” means that you know the approximate location (residential address, address of medical facility, or neighborhood) of the health event. “High temporal resolution” means daily or, at a minimum, weekly counts, though yearly counts can still be helpful when modeling the impacts of air pollution policies over long periods of time. Note: this question only asks whether the city government collects this data directly. Separate questions later in the questionnaire will ask about data sharing with hospitals, ministries of health, and other groups that may have health data. | D22: ='Self-Assessment'!D44 -> 1.5 | E22: Create secure, geocoded feeds of de‑identified health data to track pollution‑related illnesses. Examples: Receive weekly asthma‑related ER visit counts by neighborhood; map clinic visits for COPD exacerbations. | H22: 1 | K22: 1 | N22: 1 | P22: 1 | R22: 1
B23: =B22+1 -> 16 | C23: Does your city track and make available data on competing risks to health and equity (e.g., drinking water quality, pesticide use, chemical exposures)? | D23: ='Self-Assessment'!D45 -> 1 | E23: Build an integrated hazard dashboard combining environmental, health, and exposure indicators. Examples: Show PM2.5 and ozone next to heat‑index alerts; visualize multi‑day wildfire smoke forecasts alongside hospital surge data. | H23: 1 | O23: 1 | R23: 1
B24: =B23+1 -> 17 | C24: *Does your city collect labor market data (e.g., by gender, race/ethnicity, age, region, occupation) on current workforce composition, sectoral vulnerabilities related to air quality policies and energy transitions, and potential for participation in green job sectors? | D24: ='Self-Assessment'!D46 -> 1 | E24: Acquire workforce and labor sector datasets to evaluate impacts of environmental policies on workers. Examples: Map diesel mechanic employment by racial or ethnic identity or country of origin; identify neighborhoods dependent on refinery‑related jobs. | H24: 1 | P24: 1 | S24: 1
B25: =B24+1 -> 18 | C25: Do you collect data on how air quality-related costs (such as energy or transportation expenses) affect households and businesses? | D25: ='Self-Assessment'!D47 -> 0 | E25: Track household energy and transportation burdens to understand economic stress linked to pollution and energy transitions. Examples: Analyze utility bill data for low‑income households; survey commute distances for car‑dependent neighborhoods. | K25: 1 | N25: 1 | S25: 1 | T25: 1
B26: =B25+1 -> 19 | C26: Are members of communities that are disproportionately impacted by air pollution engaged in the design and review of data systems that monitor labor market data and other job-related outcomes? For this question, “job-related” outcomes include opportunities to participate in job retraining, job placement, and green job creation programs. This is important because air quality policies may not be equitable if they result in economic hardship for vulnerable populations. Instead, equitable air quality policies should provide benefits to vulnerable populations, including economic and job-related benefits. | D26: ='Self-Assessment'!D48 -> 0 | E26: Hold co‑design workshops with workers and communities to shape labor data systems used in policy decisions. Examples: Host sessions with delivery drivers affected by zero emission zones; collaborate with warehouse workers on job quality indicators. | H26: 1 | Q26: 1 | T26: 1
B27: =B26+1 -> 20 | C27: Does your city collect data to track economic transitions related to air quality (e.g., shifts in employment, consumer prices, small business closures/openings)? | D27: ='Self-Assessment'!D49 -> 0 | E27: Monitor economic indicators linked to environmental transitions to anticipate job shifts or cost burdens. Examples: Track employment changes after electrifying port drayage; monitor small business costs related to new emissions standards. | K27: 1 | O27: 1 | S27: 1
B28: =B27+1 -> 21 | C28: *Does your city collect data on the combined impacts of air quality interventions on employment in economically disadvantaged communities? For example, are potential job losses or gains due to air quality interventions monitored? For this question, consider all types of “air quality interventions,”, including transitions to clean (or cleaner) energy, clean (or cleaner) transportation, clean (or cleaner) waste management systems, or any other policy or program meant to reduce air pollution. | D28: ='Self-Assessment'!D50 -> 0 | E28: Require job impact assessments for major clean air interventions to understand workforce consequences. Examples: Model job shifts from gas station closures; evaluate employment impacts of electrifying municipal fleets. | H28: 1 | N28: 1 | O28: 1 | S28: 1
B29: =B28+1 -> 22 | C29: *Does your city systematically keep track of and report data gaps (for example, missing or unavailable data) in its datasets that might disproportionately impact disadvantaged communities? For this question, “datasets” include all datasets relevant to equity analyses, such as data on health burdens, employment opportunities, economic activity, accessibility (e.g., transportation), etc. | D29: ='Self-Assessment'!D51 -> 0 | E29: Maintain a transparent registry documenting data gaps that hinder equity assessments. Examples: Note missing small business fuel use data; flag insufficient temporal coverage for neighborhood‑level PM2.5. | H29: 1 | J29: 1 | P29: 1 | Q29: 1 | T29: 1
B30: =B29+1 -> 23 | C30: Is there a mechanism (for example, regular meetings in neighborhoods across your city) to ensure that community-generated data and lived experiences are collected and used by city government staff for policy, resource allocation, and program design? | D30: ='Self-Assessment'!D52 -> 0 | E30: Create a platform for uploading community‑generated observations, sensor data, or complaints. Examples: Let residents submit odor events via a mobile app; allow upload of community low‑cost PM2.5 sensor data. | I30: 1 | O30: 1 | P30: 1 | Q30: 1 | R30: 1 | S30: 1 | T30: 1
B31: =B30+1 -> 24 | C31: *Does your city have systems for documentation and version control for all of its datasets? | D31: ='Self-Assessment'!D53 -> 0 | E31: Use version‑controlled repositories to store datasets, code, and metadata. Examples: Maintain emissions inventory scripts in GitHub; track model update history through tagged releases. | H31: 1 | I31: 1 | N31: 1 | P31: 1 | R31: 1 | S31: 1 | T31: 1
B32: =B31+1 -> 25 | C32: *Do air quality modeling staff collaborate with staff maintaining air quality monitoring networks so that they can bias-correct model predictions? | D32: ='Self-Assessment'!D54 -> 2 | E32: Hold regular coordination meetings between modeling and monitoring teams to align assumptions and calibration. Examples: Update modelers on new monitor calibration methods; inform monitoring teams about modeling parameter changes. | I32: 1 | K32: 1 | L32: 1 | P32: 1 | Q32: 1 | R32: 1
B34: =B32 -> 25 | C34: Data Partnerships and Linkages | D34: Score | E34: Recommendations | H34: 1 | I34: 1 | J34: 1 | K34: 1 | L34: 1 | M34: 1 | N34: 1 | O34: 1 | P34: 1 | Q34: 1 | R34: 1 | S34: 1 | T34: 1
B35: =B34+1 -> 26 | C35: *Does your city employ staff or consultants responsible for maintaining and linking air quality, environmental, demographic, health, economic, and other datasets and data pipelines? A “data pipeline” can include computing scripts–often in Python, R, or a similar language–that can make data available for analysis and sharing. | D35: ='Self-Assessment'!D57 -> 1 | E35: Assign a dedicated data engineering team to maintain pipelines and ensure data quality. Examples: Automate ingestion of real‑time sensor feeds; implement validation checks for emissions updates. | H35: 1 | I35: 1 | N35: 1 | R35: 1
B36: =B35+1 -> 27 | C36: *Has your city established data sharing partnerships between each department within your city that collects datasets that are important for analyzing the equity impacts of air quality policies? These departments in your city may include environmental and air quality departments, planning departments, health departments, transportation departments, and economic development or employment departments. Partnerships may take many forms, including regularly scheduled communication among departments, cross-department working groups, or data sharing agreements and Memorandums of Understanding. | D36: ='Self-Assessment'!D58 -> 1.5 | E36: Establish formal agreements between departments to standardize data sharing. Examples: Sign a Memorandum of Understanding (MOU) enabling health and environment departments to share de‑identified health data; formalize sharing of traffic data from transportation agencies. | H36: 1 | I36: 1 | P36: 1 | T36: 1
B37: =B36+1 -> 28 | C37: *Has your city established partnerships and processes to share air quality data with relevant officials in other levels of government, including state / provincial and national levels, that affect your city? Relevant officials may include those in ministries of health, public health, environment, transportation, economic development, infrastructure, and others. | D37: ='Self-Assessment'!D59 -> 2 | E37: Create standardized exports of air quality data to state-level or national authorities. Examples: Send monthly PM2.5 aggregates to the state air board; provide quarterly NO2 reports to national agencies. | H37: 1 | I37: 1 | P37: 1 | R37: 1 | T37: 1
B38: =B37+1 -> 29 | C38: *Has your city established partnerships and processes to share health and economic impact/disparities data with relevant officials in other levels of government, including state / provincial and national levels, that affect your city? Relevant officials may include those in ministries of health, public health, environment, transportation, economic development, infrastructure, and others. | D38: ='Self-Assessment'!D60 -> 1 | E38: Share health and environmental disparity data with higher-level (e.g., state or national) governments to support funding and policy alignment. Examples: Report racial disparities in asthma to national environmental protection ministries; share cumulative burden maps with national environmental justice offices (if any). | H38: 1 | I38: 1 | P38: 1 | R38: 1 | S38: 1 | T38: 1
B39: =B38+1 -> 30 | C39: Are satellite products linked with other air pollution monitoring data and with health and economic data (e.g., hospitalizations, asthma prevalence)? Satellite-derived air quality data can complement air quality monitoring data, particularly where monitoring data is sparse. | D39: ='Self-Assessment'!D61 -> 1.5 | E39: Use satellite‑based datasets to fill spatial gaps in monitoring coverage. Examples: Blend TROPOMI NO2 with ground monitors; use MODIS AOD to estimate PM2.5 in rural outskirts. | K39: 1 | L39: 1 | O39: 1 | R39: 1
B40: =B39+1 -> 31 | C40: *Does your city have the capacity to link air pollution model data (versus monitor data), particularly where either regulatory or low-cost air pollution monitor data is sparse? Air pollution model data (rather than monitor-based data) are often produced by outside experts. Thus, model-based data often needs to be linked. This question asks whether your city has the capacity to link this type of data. | D40: ='Self-Assessment'!D62 -> 1.5 | E40: Use modeled estimates when monitors are sparse or absent. Examples: Use CMAQ for industrial zones without sensors; apply WRF‑Chem for wildfire‑smoke scenarios. | L40: 1 | N40: 1 | R40: 1
B41: =B40+1 -> 32 | C41: Does the city or sponsor have access to long-term air quality monitoring data from national or state / provincial governments? By “long-term,” this question refers to data collected over several years. Ideally, this data will be at high spatial and temporal (e.g., daily) resolution as well. | D41: ='Self-Assessment'!D63 -> 2 | E41: Import multi‑year regional datasets to strengthen long‑term analyses. Examples: Incorporate a decade of ozone data from state networks; use 15 years of PM2.5 trends from national sites. | L41: 1 | N41: 1 | R41: 1
B42: =B41+1 -> 33 | C42: Does your city have access to historical meteorological data for your city and the surrounding areas that can be linked to other data sources? Historical data can be helpful when estimating air pollution over time. | D42: ='Self-Assessment'!D64 -> 2 | E42: Integrate historical meteorological records for trend analysis and modeling. Examples: Include 20‑year wind roses in source‑apportionment; use multi‑decade temperature data to study heat‑pollution interactions. | L42: 1 | N42: 1 | R42: 1
B43: =B42+1 -> 34 | C43: Can your city obtain and link data from low-cost sensors maintained by non-governmental organizations or private individuals? | D43: ='Self-Assessment'!D65 -> 2 | E43: If possible, build APIs to ingest community sensor data with automated quality checks. Examples: Validate PurpleAir sensors using co‑located reference monitors; automatically remove spurious humidity‑driven spikes. | H43: 1 | L43: 1 | O43: 1 | R43: 1
B44: =B43+1 -> 35 | C44: Is dedicated technical support provided to community groups managing their own low-cost sensor projects to ensure data quality and sensor calibration? | D44: ='Self-Assessment'!D66 -> 1 | E44: Run calibration clinics to help residents maintain sensor accuracy. Examples: Host weekend calibration events at libraries; provide loaner calibration equipment for community groups. | I44: 1 | J44: 1 | L44: 1 | N44: 1 | P44: 1 | T44: 1
B45: =B44+1 -> 36 | C45: Is your city able to link and map yearly data on instances of floods, heat waves, toxic chemical contamination, and other environmental burdens? | D45: ='Self-Assessment'!D67 -> 0 | E45: Integrate long‑term environmental burden datasets into a unified GIS platform. Examples: Combine diesel truck corridor maps from 2010–2025; merge historical noise data with PM2.5 burdens. | I45: 1 | N45: 1 | R45: 1
B46: =B45+1 -> 37 | C46: *Does your city link data on housing conditions, energy use patterns, household activities and behaviors, and indoor air pollutant sources? | D46: ='Self-Assessment'!D68 -> 0 | E46: Link housing and indoor‑source datasets to understand compounded risks. Examples: Overlay gas stove prevalence with poor ventilation buildings; map old HVAC systems in wildfire smoke‑prone areas. | K46: 1 | L46: 1 | O46: 1 | T46: 1
B47: =B46+1 -> 38 | C47: *Are emission and/or air quality datasets linked with workforce data (e.g., employment sectors, wages, occupational health)? | D47: ='Self-Assessment'!D69 -> 0 | E47: Link emissions hotspots with wage, employment, and economic data. Examples: Overlay warehouse clusters with low‑wage worker density; compare refinery‑adjacent neighborhoods' income levels. | L47: 1 | O47: 1 | S47: 1
B48: =B47+1 -> 39 | C48: Are multiple years of historical land use and zoning data available to link to other data sets? This type of data linkage can support air quality projections, health impact projections, and economic policy impact projections, among other topics. | D48: ='Self-Assessment'!D70 -> 1.5 | E48: Digitize historical zoning maps to understand legacy drivers of pollution patterns. Examples: Scan older industrial zoning maps. | M48: 1 | N48: 1 | O48: 1 | S48: 1
B49: =B48+1 -> 40 | C49: *Does your city link source-specific emissions monitoring data to health and economic datasets? For example, traffic-related NO2 data could be linked with childhood asthma rates, or shipping sulfur data could be linked with respiratory hospitalizations. | D49: ='Self-Assessment'!D71 -> 0 | E49: Connect emissions from specific sources to localized health outcomes. Examples: Link refinery SO2 levels to asthma visit clusters; map traffic‑related NO2 to cardiovascular incidents. | M49: 1 | O49: 1 | P49: 1 | R49: 1
B51: =B49 -> 40 | C51: Data Disaggregation and Integration | D51: Score | E51: Recommendations | H51: 1 | I51: 1 | J51: 1 | K51: 1 | L51: 1 | M51: 1 | N51: 1 | O51: 1 | P51: 1 | Q51: 1 | R51: 1 | S51: 1 | T51: 1
B52: =B51+1 -> 41 | C52: *Does your city map historical data (e.g., data over many years) on environmental burdens (air pollution, heat waves, floods, chemical exposures, etc.) and social variables (including poverty rates, migration status, race / ethnicity of residents, etc.) across neighborhoods? Put differently, can you visualize on a map the number of environmental burdens each neighborhood in your city has experienced over time to understand whether and where vulnerable populations may face higher levels of total environmental burdens? Burdens may include floods, heat waves, toxic chemical contamination, and other environmental burdens? | D52: ='Self-Assessment'!D74 -> 0 | E52: Map cumulative burdens combining environmental, social, and economic stressors. Examples: Combine PM2.5, heat, and truck‑traffic metrics; integrate pollution with poverty and overcrowding data. | H52: 1 | K52: 1 | N52: 1 | O52: 1 | R52: 1
B53: =B52+1 -> 42 | C53: *Is your city able to disaggregate air quality data to measure how different groups in your city–and particularly vulnerable and marginalized groups–are exposed to different levels of air pollution? This process generally requires cities to be able to link and map sociodemographic and air pollution data, and to understand both (1) how air pollution differs across neighborhoods and (2) demographic characteristics of groups living in highly polluted neighborhoods. | D53: ='Self-Assessment'!D75 -> 0 | E53: Overlay demographic data on exposure maps to detect inequities. Examples: Compare PM2.5 by racial or ethnic identity (or country of origin, nativity, etc) across neighborhood units; examine ozone differences by income levels. | K53: 1 | L53: 1 | N53: 1 | O53: 1 | R53: 1
B54: =B53+1 -> 43 | C54: *Are you able to disaggregate all other environmental data sources–including those measuring point / source emissions, meteorology, floods, and chemical use–by sociodemographic characteristics? As in the question above related to air pollution data, this ability is central to understanding health and economic equity impacts of air pollution. | D54: ='Self-Assessment'!D76 -> 0 | E54: Require demographic disaggregation across all environmental datasets. Examples: Break pollution exposure by age groups under 5 and over 65; map burdens for households with non-native language speakers. | K54: 1 | N54: 1 | O54: 1 | T54: 1
B55: =B54+1 -> 44 | C55: *Can your city disaggregate labor market and economic data sources--including those job creation, job loss, and other economic costs-–by sociodemographic characteristics? | D55: ='Self-Assessment'!D77 -> 0 | E55: Disaggregate labor and economic datasets to reveal inequities. Examples: Analyze job quality for port truck drivers by education; compare wages for workers in high pollution industries. | K55: 1 | N55: 1 | O55: 1 | S55: 1
B56: =B55+1 -> 45 | C56: *Are all health outcomes related to air pollution exposure disaggregated by demographics such as race, income, age, gender, and geography? | D56: ='Self-Assessment'!D78 -> 0 | E56: Require de‑identified, demographically stratified health outcomes. Examples: Publish asthma ED visits by income bracket; track COPD hospitalizations by age group. | K56: 1 | N56: 1 | O56: 1 | R56: 1
B57: =B56+1 -> 46 | C57: *Does your city disaggregate air pollution, environmental, health, and economic data by multiple demographics simultaneously? For example, some cities may disaggregate air pollution exposure by one characteristic (e.g., nativity) at a time. However, more detailed equity analyses consider the impact of intersecting facets of identity and social position. As such, they may disaggregate data based on two or more characteristics (e.g., nativity and poverty status) at the same time. In these cases, you might consider how air pollution exposure differs among, for example, low-income migrant residents, high-income migrant residents, low-income native residents, and high-income native residents. | D57: ='Self-Assessment'!D79 -> 0 | E57: Conduct intersectional analyses to understand overlapping vulnerabilities. Examples: Study exposure among low‑income seniors; analyze pollution burdens for disabled residents in industrial zones. | K57: 1 | N57: 1 | O57: 1 | T57: 1
B58: =B57+1 -> 47 | C58: Do models incorporate local source contributions to identify drivers of inequitable exposures using resident-collected air quality data that is integrated with official datasets? | D58: ='Self-Assessment'!D80 -> 0 | E58: Use community sensors to refine source attribution and exposure tracking. Examples: Detect truck traffic PM spikes during peak hours; identify smoke intrusions during backyard burning. | J58: 1 | L58: 1 | M58: 1 | N58: 1 | O58: 1 | P58: 1 | T58: 1
B59: =B58+1 -> 48 | C59: *Do your city’s analyses incorporate spatially and temporally aligned (i.e., “harmonized”) demographic, air quality, health, and economic outcome data? In other words, if you use demographic, air quality, health, and economic data in your analyses, were the various types of data collected during the same time period and at the same spatial scale (for example., street-level, neighborhood-level, city-level, province-level, etc.)? | D59: ='Self-Assessment'!D81 -> 0 | E59: Standardize spatial and temporal units across datasets for comparability. Examples: Convert all PM measurements to hourly averages (if possible); align demographic data to the same neighborhood boundaries. | H59: 1 | K59: 1 | N59: 1 | O59: 1 | R59: 1
B60: =B59+1 -> 49 | C60: Are community-generated data sources and data from lived experiences integrated into official city data sources? | D60: ='Self-Assessment'!D82 -> 0 | E60: Include qualitative community reports alongside quantitative datasets. Examples: Add odor complaints to refinery datasets; include residents’ noise logs near highways. | I60: 1 | M60: 1 | O60: 1 | P60: 1 | R60: 1 | T60: 1
B62: =B60 -> 49 | C62: Data Analysis and Modeling | D62: Score | E62: Recommendations | H62: 1 | I62: 1 | J62: 1 | K62: 1 | L62: 1 | M62: 1 | N62: 1 | O62: 1 | P62: 1 | Q62: 1 | R62: 1 | S62: 1 | T62: 1
B63: =B62+1 -> 50 | C63: *Does your city have access to computing resources including computers and statistical analysis software (e.g., R, SAS, or similar software, as well as GIS software) that can (1) process large-scale datasets and (2) estimate differences in air pollution risks across different population groups? It is important that these computing resources are powerful enough to handle large datasets and to estimate how health and economic outcomes are affected by air pollution (i.e., so-called “exposure-response datasets and risk models”). | D63: ='Self-Assessment'!D85 -> 1 | E63: Provide adequate computing infrastructure for advanced modeling and analyses. Examples: Offer cloud‑based workspaces for dispersion modeling; supply GPU resources for machine‑learning exposure estimates. | H63: 1 | N63: 1 | R63: 1
B64: =B63+1 -> 51 | C64: Does your city use open-source data analysis tools (e.g., R, QGIS) for its analyses? Using open-source tools can ensure your city’s technical capacity is robust because they do not require your city to purchase new software every few years. | D64: ='Self-Assessment'!D86 -> 0 | E64: Use open‑source tools for transparency and reproducibility. Examples: Use R for epidemiological models; use QGIS for mapping cumulative burdens. | H64: 1 | I64: 1 | N64: 1 | R64: 1
B65: =B64+1 -> 52 | C65: *Does your city systematically measure the effects of air quality policies to ensure they reduce inequities in air pollution exposure and related health economic effects? For example, the AQUA tool from C40 is one tool that can be used to measure health effects, but your city may choose other tools for this purpose. | D65: ='Self-Assessment'!D87 -> 1 | E65: Conduct before‑and‑after policy analyses to measure real‑world impact. Examples: Compare PM2.5 (or total truck traffic) before and after truck‑route changes; assess ozone improvements after industrial emission reductions. | J65: 1 | L65: 1 | P65: 1 | S65: 1 | T65: 1
B66: =B65+1 -> 53 | C66: *Are health risks from air pollution explicitly modeled for multiple demographics, and do these risks consider non-chemical stressors? | D66: ='Self-Assessment'!D88 -> 0 | E66: Model health risks using multi‑pollutant exposures and demographic factors. Examples: Estimate asthma risk increases from PM2.5 and NO2 combined; evaluate cardiovascular risks from long‑term ozone exposure. | K66: 1 | O66: 1 | R66: 1
B67: =B66+1 -> 54 | C67: Are data fusion techniques used to combine remote sensing, ground-based, and modeled data to enhance exposure assessment? | D67: ='Self-Assessment'!D89 -> 1 | E67: Apply data fusion methods combining monitors, satellites, and models. Examples: Use AOD satellite‑derived PM2.5 blended with ground data; integrate WRF‑Chem outputs with local sensors. | L67: 1 | N67: 1 | O67: 1 | R67: 1 | S67: 1 | T67: 1
B68: =B67+1 -> 55 | C68: Are model assumptions and data limitations clearly documented and communicated? | D68: ='Self-Assessment'!D90 -> 1 | E68: Publish metadata documenting methods, assumptions, and uncertainties. Examples: Provide calibration uncertainty for monitors; include model‑bias estimates in reports. | K68: 1 | P68: 1 | Q68: 1 | R68: 1
B69: =B68+1 -> 56 | C69: Are exposure models evaluated for accuracy where monitoring data may be sparse? | D69: ='Self-Assessment'!D91 -> 1 | E69: Validate model results using independent datasets. Examples: Compare modeled PM2.5 to anchor monitors; compare modeled NO2 to satellite retrievals. | K69: 1 | L69: 1 | N69: 1 | R69: 1
B70: =B69+1 -> 57 | C70: Are appropriate concentration–response functions available and applied? | D70: ='Self-Assessment'!D92 -> 0 | E70: Use locally relevant concentration‑response functions for health analyses. Examples: Apply neighborhood‑specific asthma incidence–PM2.5 coefficients if available; use local cardiovascular response functions. | K70: 1 | O70: 1 | R70: 1
B71: =B70+1 -> 58 | C71: *Are baseline population and health outcome incidence data available? | D71: ='Self-Assessment'!D93 -> 0 | E71: Publish regularly updated population and health baseline datasets. Examples: Release 2026 population denominators; update asthma incidence base rates yearly. | K71: 1 | O71: 1 | R71: 1
B72: =B71+1 -> 59 | C72: *Are analyses stratified by socio-demographic groups to assess whether vulnerable populations benefit equally from interventions? | D72: ='Self-Assessment'!D94 -> 0 | E72: Stratify policy impact analyses across demographic groups. Examples: Evaluate benefits of a wood stove ban by income quartile; assess exposure reductions among children after street redesign. | K72: 1 | N72: 1 | T72: 1
B73: =B72+1 -> 60 | C73: Is population-specific epidemiological literature used for equity analysis? (i.e., using research from/with affected populations) | D73: ='Self-Assessment'!D95 -> 0 | E73: Use epidemiological studies from comparable or local populations. Examples: Apply findings from a nearby county’s asthma cohort; use state‑level particulate‑mortality research. | K73: 1 | Q73: 1 | R73: 1
B74: =B73+1 -> 61 | C74: *Do evaluations attempt to assess whether health and economic disparities among marginalized groups (compared to groups who are not marginalized) from air pollution and air quality policies are narrowing or widening over time? | D74: ='Self-Assessment'!D96 -> 0 | E74: Track multi‑year trends in environmental and health disparities. Examples: Monitor 15‑year NO2 inequity trends; track long‑term changes in asthma rates in environmental justice communities. | I74: 1 | O74: 1 | T74: 1
B75: =B74+1 -> 62 | C75: *Are policy-based scenarios evaluated for distributional fairness (who benefits most/least)? | D75: ='Self-Assessment'!D97 -> 0 | E75: Assess which groups benefit most or least from new policies. Examples: Identify which neighborhoods saw the biggest PM2.5 drop after port electrification; determine which groups saw minimal improvement. | K75: 1 | P75: 1 | Q75: 1 | R75: 1 | S75: 1 | T75: 1
B76: =B75+1 -> 63 | C76: *Are health and equity outcomes among marginalized, vulnerable, or particularly susceptible groups (children, elderly, people with chronic illness) explicitly quantified? | D76: ='Self-Assessment'!D98 -> 0 | E76: Quantify distribution of benefits for vulnerable populations. Examples: Measure reductions in indoor PM2.5 for low‑income homes; calculate smoke‑day risk reductions for medically fragile residents. | K76: 1 | N76: 1 | R76: 1
B77: =B76+1 -> 64 | C77: *Do health and economic impact assessments of air quality policies include analyses of differential burdens across diverse groups and local economies (e.g., low income workers)? | D77: ='Self-Assessment'!D99 -> 0 | E77: Analyze how environmental burdens differ across communities. Examples: Compare highway noise levels across census tracts; evaluate heat risk disparities in tree‑poor neighborhoods. | J77: 1 | K77: 1 | N77: 1 | P77: 1 | R77: 1 | S77: 1
B78: =B77+1 -> 65 | C78: *Does your city analyze health and economic costs associated with policy compliance or adaptation and how this is distributed across communities and businesses of different sizes? | D78: ='Self-Assessment'!D100 -> 0 | E78: Evaluate how compliance and adaptation costs vary across groups. Examples: Study EV‑fleet upgrade costs for small delivery firms; analyze HVAC‑retrofit burdens for low‑income landlords. | J78: 1 | O78: 1 | T78: 1
B79: =B78+1 -> 66 | C79: *Does your city have programs or policies to ensure that community members from marginalized, vulnerable, or disproportionately exposed areas are engaged in decisionmaking about how to interpret and analyze air pollution data from your city? | D79: ='Self-Assessment'!D101 -> 0 | E79: Create resident interpretation panels to review findings. Examples: Hold quarterly map review sessions with community reps; invite residents to annotate exposure graphs. | H79: 1 | Q79: 1 | T79: 1
B80: =B79+1 -> 67 | C80: Do evaluations report whether health outcomes (e.g., fewer hospital visits, lower asthma rates) improve after interventions? | D80: ='Self-Assessment'!D102 -> 0 | E80: Publish health improvements after interventions. Examples: Report fewer asthma visits following roadway redesign (if any); show reduced ER visits after indoor air filter installations (if any). | H80: 1 | J80: 1 | N80: 1 | Q80: 1 | R80: 1
B81: =B80+1 -> 68 | C81: Do marginalized groups or their representatives have a clear mechanism to provide input on—or object to—the data and assumptions underpinning equity impact analyses? | D81: ='Self-Assessment'!D103 -> 0 | E81: Provide formal feedback systems for residents to challenge assumptions. Examples: Online forms for disputing model results; structured review meetings to correct data errors. | H81: 1 | K81: 1 | Q81: 1 | R81: 1 | T81: 1
B83: =B81 -> 68 | C83: Data Communication | D83: Score | E83: Recommendations | H83: 1 | I83: 1 | J83: 1 | K83: 1 | L83: 1 | M83: 1 | N83: 1 | O83: 1 | P83: 1 | Q83: 1 | R83: 1 | S83: 1 | T83: 1
B84: =B83+1 -> 69 | C84: *Can the public access your city’s air quality and emissions data for free? Public access could include internet-based tools or apps. Note: This specific question refers only to the ability of the public to access your data. It does not refer to whether the public actually uses whatever tools may exist. | D84: ='Self-Assessment'!D106 -> 1 | E84: Maintain a public open data portal for real‑time and historical air data. Examples: Post daily PM2.5 levels downloadable in CSV; provide multi‑year pollutant trend files. | H84: 1 | I84: 1 | K84: 1 | M84: 1 | N84: 1 | O84: 1 | T84: 1
B85: =B84+1 -> 70 | C85: *Are public-facing data platforms designed with community input to ensure accessibility (e.g., mobile-friendly, low-data consumption, interactive maps) rather than relying solely on raw data files? | D85: ='Self-Assessment'!D107 -> 2 | E85: Co‑design public‑facing platforms with accessibility and multilingual features. Examples: Offer Spanish and Chinese versions of dashboards (or versions in other locally relevant languages); make mobile friendly visualizations. | J85: 1 | L85: 1 | M85: 1 | O85: 1 | Q85: 1 | T85: 1
B86: =B85+1 -> 71 | C86: *Are real-time air quality alerts and warnings, resources, and recommendations for protective actions available to residents in all neighborhoods in your city? For this question, consider whether these resources (alerts, recommendations, etc.) are disseminated through multiple platforms, including websites, apps, text messaging, or other media. | D86: ='Self-Assessment'!D108 -> 1.5 | E86: Provide real‑time alerts through multiple communication channels. Examples: SMS smoke alerts during wildfires; radio notices during industrial incidents. | J86: 1 | O86: 1 | T86: 1
B87: =B86+1 -> 72 | C87: Does your city track public engagement with any publicly available air quality data? This could include simply counting the number of visits to relevant webpages, and it would be a helpful datapoint to consider when building equitable air quality policies. | D87: ='Self-Assessment'!D109 -> 1.5 | E87: Track engagement metrics to evaluate communication effectiveness. Examples: Count app downloads during wildfire season; measure webpage visits on high pollution days. | H87: 1 | N87: 1 | T87: 1
B88: =B87+1 -> 73 | C88: *Are policy effects evaluated and reported back to communities in a transparent and publicly accessible way? | D88: ='Self-Assessment'!D110 -> 1 | E88: Hold public meetings and publish plain language summaries of results. Examples: Quarterly briefings with neighborhood groups; infographics explaining new regulations. | H88: 1 | K88: 1 | Q88: 1 | T88: 1
B89: =B88+1 -> 74 | C89: Are there frequent, accessible training opportunities provided to communities and neighborhoods on how to use monitors, and store/access and interpret air quality data? | D89: ='Self-Assessment'!D111 -> 0 | E89: Offer community training workshops on air‑quality concepts and tools. Examples: Teach residents how to interpret PM2.5 graphs; train volunteers to maintain sensors. | I89: 1 | Q89: 1 | T89: 1
B90: =B89+1 -> 75 | C90: Is air monitoring data translated into non-technical summaries and available in the primary languages spoken by residents in the monitored communities? | D90: ='Self-Assessment'!D112 -> 0 | E90: Provide multilingual, accessible translations of data and visualizations. Examples: Infographics in Spanish and Vietnamese (or other locally relevant languages); audio versions for visually impaired residents. | L90: 1 | Q90: 1 | T90: 1
B91: =B90+1 -> 76 | C91: *Are local community members and business leaders actively engaged in decision-making regarding data sources, data use, and data analyses, not just consulted after the fact? | D91: ='Self-Assessment'!D113 -> 1.5 | E91: Include community and business leaders in data governance structures. Examples: Invite trucking company reps to advisory committees; include environmental justice organizations in decision meetings. | I91: 1 | Q91: 1 | S91: 1
B92: =B91+1 -> 77 | C92: *Are stakeholders within the government able to access and distribute quality-assured air quality data? | D92: ='Self-Assessment'!D114 -> 1 | E92: Ensure government staff have training and access to high quality datasets. Examples: Provide GIS training to health department analysts; teach environmental staff how to query emissions databases. | L92: 1 | O92: 1 | P92: 1 | T92: 1
B93: =B92+1 -> 78 | C93: Are equity-focused and community organizations meaningfully included in governance and capacity-building on issues related to data sources, data use, and data analysis, and not just technical agencies? | D93: ='Self-Assessment'!D115 -> 1 | E93: Include equity organizations in data system co‑design and capacity building. Examples: Collaborate with environmental justice nonprofits; train neighborhood coalitions in data interpretation. | I93: 1 | Q93: 1 | T93: 1
B94: =B93+1 -> 79 | C94: Are mechanisms in place to ensure that the data and findings used for just energy transition planning and air quality policy implementation are communicated to and validated by women, youth, Indigenous peoples, racial/ethnic minorities, and other frontline communities relevant to your city and context? | D94: ='Self-Assessment'!D116 -> 0 | E94: Conduct targeted outreach to communities most affected by pollution. Examples: Distribute wildfire smoke flyers in frontline neighborhoods; host tabling events at local markets. | J94: 1 | Q94: 1 | R94: 1
B95: =B94+1 -> 80 | C95: Are the health sector and community organizations actively engaged in decision-making regarding data sources, data use, and data analyses, not just consulted after the fact? | D95: ='Self-Assessment'!D117 -> 0 | E95: Form a joint data council linking health, environment, labor, and community stakeholders with formal decision power. Examples: Monthly cross‑agency council meetings; annual community review sessions for priority setting. | I95: 1 | Q95: 1 | T95: 1

Sheet Definitions
C3: EQuiPD: Equity in Air Quality Policy & Data Ecosystem
C4: Definitions
C6: Categories
C7: Data-sharing partnerships & management tools
C8: Robust capacity in data collection, analysis, and public transparency is essential for equitable air quality policies. This means systems that detect health and economic disparities, integrate diverse datasets, and map cumulative environmental burdens by community and socioeconomic status. Open access to data, strong local partnerships, and active involvement of marginalized communities in monitoring and decision-making help ensure that interventions are both effective and just. Regular, transparent reporting and evaluation of outcomes are crucial for accountability and ongoing policy improvement.
C10: City/institutional buy-in, capacity building & training
C11: Building and sustaining robust technical and organizational capacity is vital for equitable air quality policy-making. This involves having political buy-in to channel resources and mandate and accessible tools and trained staff to map, analyze, and communicate air quality gradients, their health and equity impacts, as well as resources for ongoing public and community training. Budgets and leadership structures must support long-term system upgrades, prioritize high-burden communities, and ensure regular, transparent evaluations—including independent audits and mechanisms for community input. Effective capacity also requires cross-sector coordination, sustained funding, and a commitment to policies that target disparity reduction and reflect the needs and diversity of the most affected populations.
C13: Public support & engagement
C14: Ensuring that air quality policy-making addresses the diverse needs of all communities, especially the most vulnerable is critical to building public support & engagement. This means collecting and sharing data on access to clean air spaces, transportation, and public warnings, while tailoring resources and risk communications in multiple formats and languages. Economic impact assessments and compliance costs should explicitly analyze and address differential burdens, and feedback mechanisms must enable meaningful input from marginalized groups. Accessible and inclusive information about air pollution, impacts from policies and live tracking of changes over team can be game changing when it comes to building public support and addressing backlash. Sustained training, participatory processes, and investments in clean air monitoring infrastructure—combined with regular evaluation of health outcomes, public accountability, and integration of citizen data—ensure that policies are both effective and equitable for populations such as low-income, elderly, Indigenous, and minority residents.
C16: Health & economic impact modeling
C17: Equitable air quality policy-making relies on comprehensive, accurate modeling and monitoring systems that explicitly quantify health and economic impacts of particular policies for vulnerable and marginalized groups. This involves ensuring exposure and scenario-based models reflect real-world conditions through collaboration with monitoring networks, validation in data-sparse areas, and integration of fine-scale demographic and economic data. Analyses must be stratified by factors such as income, age, race, and geography, translating results into meaningful, accessible formats (e.g., public dashboards, maps, and plain-language summaries) that inform both policy and community resilience efforts. Ongoing community input, transparent communication of methods and limitations, and regular updates ensure that modeling truly supports fair distribution of benefits and burdens, strengthens preparedness, and provides targeted support to those most affected by air pollution and regulatory changes.
C19: Estimating air pollution
... C41: Ensuring equitable outcomes along the five equity impact areas outlined by C40. This theme addresses equitable access to information, services, public resources, infrastructure, participation in decision-making, and physical environments for all communities, especially those historically marginalized. Questions focus on accessibility and inclusion to services, public spaces, and information as well as engagement and decision making around data.

Sheet c40_cities
A1: City | B1: Country | C1: Combined
A2: Buenos Aires | B2: Argentina | C2: =B2&" - "&A2 -> Argentina - Buenos Aires
A3: Melbourne | B3: Australia | C3: =B3&" - "&A3 -> Australia - Melbourne
A4: Sydney | B4: Australia | C4: =B4&" - "&A4 -> Australia - Sydney
A5: Dhaka (North & South) | B5: Bangladesh | C5: =B5&" - "&A5 -> Bangladesh - Dhaka (North & South)
A6: Curitiba | B6: Brazil | C6: =B6&" - "&A6 -> Brazil - Curitiba
A7: Fortaleza | B7: Brazil | C7: =B7&" - "&A7 -> Brazil - Fortaleza
A8: Rio de Janeiro | B8: Brazil | C8: =B8&" - "&A8 -> Brazil - Rio de Janeiro
A9: Salvador | B9: Brazil | C9: =B9&" - "&A9 -> Brazil - Salvador
A10: São Paulo | B10: Brazil | C10: =B10&" - "&A10 -> Brazil - São Paulo
A11: Montréal | B11: Canada | C11: =B11&" - "&A11 -> Canada - Montréal
A12: Toronto | B12: Canada | C12: =B12&" - "&A12 -> Canada - Toronto
A13: Vancouver | B13: Canada | C13: =B13&" - "&A13 -> Canada - Vancouver
... A98: Ho Chi Minh City | B98: Vietnam | C98: =B98&" - "&A98 -> Vietnam - Ho Chi Minh City
C99: Not listed

Sheet org_detail
A1: Abbreviation | B1: Full_Name | C1: Organization
A2: DS | B2: Data-sharing partnerships & management tools | C2: Category
A3: CB | B3: City/institutional buy-in, capacity building & training | C3: Category
A4: PS | B4: Public support & engagement | C4: Category
A5: IM | B5: Health and economic impact modelling | C5: Category
A6: AP | B6: Estimating air pollution | C6: Category
A7: SE | B7: Source & emission inventories | C7: Category
A8: TC | B8: Technical Capacity | C8: Domain
A9: DI | B9: Data Integration | C9: Domain
A10: IP | B10: Internal Processes | C10: Domain
A11: PE | B11: Participation and Empowerment | C11: Domain
A12: DE | B12: Distributional Equity | C12: Equity Theme
... A14: AI | B14: Access and Inclusivity | C14: Equity Theme

Sheet QCount
A1: EQuiPD | F1: EQuiPD
B2: This page counts the number of questions at the intersection of each category, domain, and equity theme. Areas with fewer questions may be areas of opportunity to further expand or consider revising scoring mapping.
B4: Data-sharing partnerships & management tools
C6: Equity Themes
B7: Domains | C7: Distributional Equity | D7: Socioeconomic Resilience and Opportunity | E7: Access and Inclusivity
B8: Technical Capacity | C8: =IFERROR(COUNTIFS('Self-Assessment'!H$29:H$313,1,'Self-Assessment'!N$29:N$313,1,'Self-Assessment'!R$29:R$313,1),"") -> 8 | D8: =IFERROR(COUNTIFS('Self-Assessment'!H$29:H$313,1,'Self-Assessment'!N$29:N$313,1,'Self-Assessment'!S$29:S$313,1),"") -> 4 | E8: =IFERROR(COUNTIFS('Self-Assessment'!H$29:H$313,1,'Self-Assessment'!N$29:N$313,1,'Self-Assessment'!T$29:T$313,1),"") -> 4
B9: Data Integration | C9: =IFERROR(COUNTIFS('Self-Assessment'!H$29:H$313,1,'Self-Assessment'!O$29:O$313,1,'Self-Assessment'!R$29:R$313,1),"") -> 5 | D9: =IFERROR(COUNTIFS('Self-Assessment'!H$29:H$313,1,'Self-Assessment'!O$29:O$313,1,'Self-Assessment'!S$29:S$313,1),"") -> 2 | E9: =IFERROR(COUNTIFS('Self-Assessment'!H$29:H$313,1,'Self-Assessment'!O$29:O$313,1,'Self-Assessment'!T$29:T$313,1),"") -> 1
B10: Internal Processes | C10: =IFERROR(COUNTIFS('Self-Assessment'!H$29:H$313,1,'Self-Assessment'!P$29:P$313,1,'Self-Assessment'!R$29:R$313,1),"") -> 5 | D10: =IFERROR(COUNTIFS('Self-Assessment'!H$29:H$313,1,'Self-Assessment'!P$29:P$313,1,'Self-Assessment'!S$29:S$313,1),"") -> 5 | E10: =IFERROR(COUNTIFS('Self-Assessment'!H$29:H$313,1,'Self-Assessment'!P$29:P$313,1,'Self-Assessment'!T$29:T$313,1),"") -> 6
B11: Participation and Empowerment | C11: =IFERROR(COUNTIFS('Self-Assessment'!H$29:H$313,1,'Self-Assessment'!Q$29:Q$313,1,'Self-Assessment'!R$29:R$313,1),"") -> 3 | D11: =IFERROR(COUNTIFS('Self-Assessment'!H$29:H$313,1,'Self-Assessment'!Q$29:Q$313,1,'Self-Assessment'!S$29:S$313,1),"") -> 2 | E11: =IFERROR(COUNTIFS('Self-Assessment'!H$29:H$313,1,'Self-Assessment'!Q$29:Q$313,1,'Self-Assessment'!T$29:T$313,1),"") -> 7
B13: City/institutional buy-in, capacity building & training
C15: Equity Themes
B16: Domains | C16: Distributional Equity | D16: Socioeconomic Resilience and Opportunity | E16: Access and Inclusivity
B17: Technical Capacity | C17: =IFERROR(COUNTIFS('Self-Assessment'!I$29:I$313,1,'Self-Assessment'!N$29:N$313,1,'Self-Assessment'!R$29:R$313,1),"") -> 4 | D17: =IFERROR(COUNTIFS('Self-Assessment'!I$29:I$313,1,'Self-Assessment'!N$29:N$313,1,'Self-Assessment'!S$29:S$313,1),"") -> 1 | E17: =IFERROR(COUNTIFS('Self-Assessment'!I$29:I$313,1,'Self-Assessment'!N$29:N$313,1,'Self-Assessment'!T$29:T$313,1),"") -> 3
B18: Data Integration | C18: =IFERROR(COUNTIFS('Self-Assessment'!I$29:I$313,1,'Self-Assessment'!O$29:O$313,1,'Self-Assessment'!R$29:R$313,1),"") -> 2 | D18: =IFERROR(COUNTIFS('Self-Assessment'!I$29:I$313,1,'Self-Assessment'!O$29:O$313,1,'Self-Assessment'!S$29:S$313,1),"") -> 1 | E18: =IFERROR(COUNTIFS('Self-Assessment'!I$29:I$313,1,'Self-Assessment'!O$29:O$313,1,'Self-Assessment'!T$29:T$313,1),"") -> 4
B19: Internal Processes | C19: =IFERROR(COUNTIFS('Self-Assessment'!I$29:I$313,1,'Self-Assessment'!P$29:P$313,1,'Self-Assessment'!R$29:R$313,1),"") -> 6 | D19: =IFERROR(COUNTIFS('Self-Assessment'!I$29:I$313,1,'Self-Assessment'!P$29:P$313,1,'Self-Assessment'!S$29:S$313,1),"") -> 3 | E19: =IFERROR(COUNTIFS('Self-Assessment'!I$29:I$313,1,'Self-Assessment'!P$29:P$313,1,'Self-Assessment'!T$29:T$313,1),"") -> 7
B20: Participation and Empowerment | C20: =IFERROR(COUNTIFS('Self-Assessment'!I$29:I$313,1,'Self-Assessment'!Q$29:Q$313,1,'Self-Assessment'!R$29:R$313,1),"") -> 2 | D20: =IFERROR(COUNTIFS('Self-Assessment'!I$29:I$313,1,'Self-Assessment'!Q$29:Q$313,1,'Self-Assessment'!S$29:S$313,1),"") -> 2 | E20: =IFERROR(COUNTIFS('Self-Assessment'!I$29:I$313,1,'Self-Assessment'!Q$29:Q$313,1,'Self-Assessment'!T$29:T$313,1),"") -> 4
B22: Public support & engagement
C24: Equity Themes
B25: Domains | C25: Distributional Equity | D25: Socioeconomic Resilience and Opportunity | E25: Access and Inclusivity
B26: Technical Capacity | C26: =IFERROR(COUNTIFS('Self-Assessment'!J$29:J$313,1,'Self-Assessment'!N$29:N$313,1,'Self-Assessment'!R$29:R$313,1),"") -> 3 | D26: =IFERROR(COUNTIFS('Self-Assessment'!J$29:J$313,1,'Self-Assessment'!N$29:N$313,1,'Self-Assessment'!S$29:S$313,1),"") -> 3 | E26: =IFERROR(COUNTIFS('Self-Assessment'!J$29:J$313,1,'Self-Assessment'!N$29:N$313,1,'Self-Assessment'!T$29:T$313,1),"") -> 3
B27: Data Integration | C27: =IFERROR(COUNTIFS('Self-Assessment'!J$29:J$313,1,'Self-Assessment'!O$29:O$313,1,'Self-Assessment'!R$29:R$313,1),"") -> 1 | D27: =IFERROR(COUNTIFS('Self-Assessment'!J$29:J$313,1,'Self-Assessment'!O$29:O$313,1,'Self-Assessment'!S$29:S$313,1),"") -> 1 | E27: =IFERROR(COUNTIFS('Self-Assessment'!J$29:J$313,1,'Self-Assessment'!O$29:O$313,1,'Self-Assessment'!T$29:T$313,1),"") -> 5
B28: Internal Processes | C28: =IFERROR(COUNTIFS('Self-Assessment'!J$29:J$313,1,'Self-Assessment'!P$29:P$313,1,'Self-Assessment'!R$29:R$313,1),"") -> 2 | D28: =IFERROR(COUNTIFS('Self-Assessment'!J$29:J$313,1,'Self-Assessment'!P$29:P$313,1,'Self-Assessment'!S$29:S$313,1),"") -> 4 | E28: =IFERROR(COUNTIFS('Self-Assessment'!J$29:J$313,1,'Self-Assessment'!P$29:P$313,1,'Self-Assessment'!T$29:T$313,1),"") -> 5
B29: Participation and Empowerment | C29: =IFERROR(COUNTIFS('Self-Assessment'!J$29:J$313,1,'Self-Assessment'!Q$29:Q$313,1,'Self-Assessment'!R$29:R$313,1),"") -> 3 | D29: =IFERROR(COUNTIFS('Self-Assessment'!J$29:J$313,1,'Self-Assessment'!Q$29:Q$313,1,'Self-Assessment'!S$29:S$313,1),"") -> 1 | E29: =IFERROR(COUNTIFS('Self-Assessment'!J$29:J$313,1,'Self-Assessment'!Q$29:Q$313,1,'Self-Assessment'!T$29:T$313,1),"") -> 2
B31: Health & economic impact modelling
C33: Equity Themes
B34: Domains | C34: Distributional Equity | D34: Socioeconomic Resilience and Opportunity | E34: Access and Inclusivity
B35: Technical Capacity | C35: =IFERROR(COUNTIFS('Self-Assessment'!K$29:K$313,1,'Self-Assessment'!N$29:N$313,1,'Self-Assessment'!R$29:R$313,1),"") -> 8 | D35: =IFERROR(COUNTIFS('Self-Assessment'!K$29:K$313,1,'Self-Assessment'!N$29:N$313,1,'Self-Assessment'!S$29:S$313,1),"") -> 3 | E35: =IFERROR(COUNTIFS('Self-Assessment'!K$29:K$313,1,'Self-Assessment'!N$29:N$313,1,'Self-Assessment'!T$29:T$313,1),"") -> 5
B36: Data Integration | C36: =IFERROR(COUNTIFS('Self-Assessment'!K$29:K$313,1,'Self-Assessment'!O$29:O$313,1,'Self-Assessment'!R$29:R$313,1),"") -> 8 | D36: =IFERROR(COUNTIFS('Self-Assessment'!K$29:K$313,1,'Self-Assessment'!O$29:O$313,1,'Self-Assessment'!S$29:S$313,1),"") -> 2 | E36: =IFERROR(COUNTIFS('Self-Assessment'!K$29:K$313,1,'Self-Assessment'!O$29:O$313,1,'Self-Assessment'!T$29:T$313,1),"") -> 4
B37: Internal Processes | C37: =IFERROR(COUNTIFS('Self-Assessment'!K$29:K$313,1,'Self-Assessment'!P$29:P$313,1,'Self-Assessment'!R$29:R$313,1),"") -> 5 | D37: =IFERROR(COUNTIFS('Self-Assessment'!K$29:K$313,1,'Self-Assessment'!P$29:P$313,1,'Self-Assessment'!S$29:S$313,1),"") -> 2 | E37: =IFERROR(COUNTIFS('Self-Assessment'!K$29:K$313,1,'Self-Assessment'!P$29:P$313,1,'Self-Assessment'!T$29:T$313,1),"") -> 1
B38: Participation and Empowerment | C38: =IFERROR(COUNTIFS('Self-Assessment'!K$29:K$313,1,'Self-Assessment'!Q$29:Q$313,1,'Self-Assessment'!R$29:R$313,1),"") -> 5 | D38: =IFERROR(COUNTIFS('Self-Assessment'!K$29:K$313,1,'Self-Assessment'!Q$29:Q$313,1,'Self-Assessment'!S$29:S$313,1),"") -> 1 | E38: =IFERROR(COUNTIFS('Self-Assessment'!K$29:K$313,1,'Self-Assessment'!Q$29:Q$313,1,'Self-Assessment'!T$29:T$313,1),"") -> 3
B41: Estimating air pollution
C43: Equity Themes
B44: Domains | C44: Distributional Equity | D44: Socioeconomic Resilience and Opportunity | E44: Access and Inclusivity
B45: Technical Capacity | C45: =IFERROR(COUNTIFS('Self-Assessment'!L$29:L$313,1,'Self-Assessment'!N$29:N$313,1,'Self-Assessment'!R$29:R$313,1),"") -> 8 | D45: =IFERROR(COUNTIFS('Self-Assessment'!L$29:L$313,1,'Self-Assessment'!N$29:N$313,1,'Self-Assessment'!S$29:S$313,1),"") -> 1 | E45: =IFERROR(COUNTIFS('Self-Assessment'!L$29:L$313,1,'Self-Assessment'!N$29:N$313,1,'Self-Assessment'!T$29:T$313,1),"") -> 5
B46: Data Integration | C46: =IFERROR(COUNTIFS('Self-Assessment'!L$29:L$313,1,'Self-Assessment'!O$29:O$313,1,'Self-Assessment'!R$29:R$313,1),"") -> 4 | D46: =IFERROR(COUNTIFS('Self-Assessment'!L$29:L$313,1,'Self-Assessment'!O$29:O$313,1,'Self-Assessment'!S$29:S$313,1),"") -> 2 | E46: =IFERROR(COUNTIFS('Self-Assessment'!L$29:L$313,1,'Self-Assessment'!O$29:O$313,1,'Self-Assessment'!T$29:T$313,1),"") -> 5
B47: Internal Processes | C47: =IFERROR(COUNTIFS('Self-Assessment'!L$29:L$313,1,'Self-Assessment'!P$29:P$313,1,'Self-Assessment'!R$29:R$313,1),"") -> 2 | D47: =IFERROR(COUNTIFS('Self-Assessment'!L$29:L$313,1,'Self-Assessment'!P$29:P$313,1,'Self-Assessment'!S$29:S$313,1),"") -> 1 | E47: =IFERROR(COUNTIFS('Self-Assessment'!L$29:L$313,1,'Self-Assessment'!P$29:P$313,1,'Self-Assessment'!T$29:T$313,1),"") -> 4
B48: Participation and Empowerment | C48: =IFERROR(COUNTIFS('Self-Assessment'!L$29:L$313,1,'Self-Assessment'!Q$29:Q$313,1,'Self-Assessment'!R$29:R$313,1),"") -> 1 | D48: =IFERROR(COUNTIFS('Self-Assessment'!L$29:L$313,1,'Self-Assessment'!Q$29:Q$313,1,'Self-Assessment'!S$29:S$313,1),"") -> 1 | E48: =IFERROR(COUNTIFS('Self-Assessment'!L$29:L$313,1,'Self-Assessment'!Q$29:Q$313,1,'Self-Assessment'!T$29:T$313,1),"") -> 4
B50: Source & emission inventories
C52: Equity Themes
B53: Domains | C53: Distributional Equity | D53: Socioeconomic Resilience and Opportunity | E53: Access and Inclusivity
B54: Technical Capacity | C54: =IFERROR(COUNTIFS('Self-Assessment'!M$29:M$313,1,'Self-Assessment'!N$29:N$313,1,'Self-Assessment'!R$29:R$313,1),"") -> 1 | D54: =IFERROR(COUNTIFS('Self-Assessment'!M$29:M$313,1,'Self-Assessment'!N$29:N$313,1,'Self-Assessment'!S$29:S$313,1),"") -> 2 | E54: =IFERROR(COUNTIFS('Self-Assessment'!M$29:M$313,1,'Self-Assessment'!N$29:N$313,1,'Self-Assessment'!T$29:T$313,1),"") -> 2
B55: Data Integration | C55: =IFERROR(COUNTIFS('Self-Assessment'!M$29:M$313,1,'Self-Assessment'!O$29:O$313,1,'Self-Assessment'!R$29:R$313,1),"") -> 3 | D55: =IFERROR(COUNTIFS('Self-Assessment'!M$29:M$313,1,'Self-Assessment'!O$29:O$313,1,'Self-Assessment'!S$29:S$313,1),"") -> 2 | E55: =IFERROR(COUNTIFS('Self-Assessment'!M$29:M$313,1,'Self-Assessment'!O$29:O$313,1,'Self-Assessment'!T$29:T$313,1),"") -> 4
B56: Internal Processes | C56: =IFERROR(COUNTIFS('Self-Assessment'!M$29:M$313,1,'Self-Assessment'!P$29:P$313,1,'Self-Assessment'!R$29:R$313,1),"") -> 3 | D56: =IFERROR(COUNTIFS('Self-Assessment'!M$29:M$313,1,'Self-Assessment'!P$29:P$313,1,'Self-Assessment'!S$29:S$313,1),"") -> 1 | E56: =IFERROR(COUNTIFS('Self-Assessment'!M$29:M$313,1,'Self-Assessment'!P$29:P$313,1,'Self-Assessment'!T$29:T$313,1),"") -> 2
B57: Participation and Empowerment | C57: =IFERROR(COUNTIFS('Self-Assessment'!M$29:M$313,1,'Self-Assessment'!Q$29:Q$313,1,'Self-Assessment'!R$29:R$313,1),"") -> 1 | D57: =IFERROR(COUNTIFS('Self-Assessment'!M$29:M$313,1,'Self-Assessment'!Q$29:Q$313,1,'Self-Assessment'!S$29:S$313,1),"") -> 3 | E57: =IFERROR(COUNTIFS('Self-Assessment'!M$29:M$313,1,'Self-Assessment'!Q$29:Q$313,1,'Self-Assessment'!T$29:T$313,1),"") -> 2

Sheet scoring_table
B1: Technical Capacity | C1: Data Integration | D1: Internal Processes | E1: Participation and Empowerment | F1: Distributional Equity | G1: Socioeconomic Resilience and Opportunity | H1: Access and Inclusivity
A2: Data-sharing partnerships & management tools | B2: =IFERROR(AVERAGEIFS('Self-Assessment'!D$29:D$313,'Self-Assessment'!H$29:H$313,1,'Self-Assessment'!N$29:N$313,1),"") -> 0.61538462 | C2: =IFERROR(AVERAGEIFS('Self-Assessment'!D$29:D$313,'Self-Assessment'!H$29:H$313,1,'Self-Assessment'!O$29:O$313,1),"") -> 0.71428571 | D2: =IFERROR(AVERAGEIFS('Self-Assessment'!D$29:D$313,'Self-Assessment'!H$29:H$313,1,'Self-Assessment'!P$29:P$313,1),"") -> 1 | E2: =IFERROR(AVERAGEIFS('Self-Assessment'!D$29:D$313,'Self-Assessment'!H$29:H$313,1,'Self-Assessment'!Q$29:Q$313,1),"") -> 0.44444444 | F2: =IFERROR(AVERAGEIFS('Self-Assessment'!D$29:D$313,'Self-Assessment'!H$29:H$313,1,'Self-Assessment'!R$29:R$313,1),"") -> 0.75 | G2: =IFERROR(AVERAGEIFS('Self-Assessment'!D$29:D$313,'Self-Assessment'!H$29:H$313,1,'Self-Assessment'!S$29:S$313,1),"") -> 0.75 | H2: =IFERROR(AVERAGEIFS('Self-Assessment'!D$29:D$313,'Self-Assessment'!H$29:H$313,1,'Self-Assessment'!T$29:T$313,1),"") -> 0.78571429
A3: City/institutional buy-in, capacity building & training | B3: =IFERROR(AVERAGEIFS('Self-Assessment'!D$29:D$313,'Self-Assessment'!I$29:I$313,1,'Self-Assessment'!N$29:N$313,1),"") -> 0.5 | C3: =IFERROR(AVERAGEIFS('Self-Assessment'!D$29:D$313,'Self-Assessment'!I$29:I$313,1,'Self-Assessment'!O$29:O$313,1),"") -> 0.25 | D3: =IFERROR(AVERAGEIFS('Self-Assessment'!D$29:D$313,'Self-Assessment'!I$29:I$313,1,'Self-Assessment'!P$29:P$313,1),"") -> 0.9375 | E3: =IFERROR(AVERAGEIFS('Self-Assessment'!D$29:D$313,'Self-Assessment'!I$29:I$313,1,'Self-Assessment'!Q$29:Q$313,1),"") -> 0.75 | F3: =IFERROR(AVERAGEIFS('Self-Assessment'!D$29:D$313,'Self-Assessment'!I$29:I$313,1,'Self-Assessment'!R$29:R$313,1),"") -> 0.66666667 | G3: =IFERROR(AVERAGEIFS('Self-Assessment'!D$29:D$313,'Self-Assessment'!I$29:I$313,1,'Self-Assessment'!S$29:S$313,1),"") -> 0.625 | H3: =IFERROR(AVERAGEIFS('Self-Assessment'!D$29:D$313,'Self-Assessment'!I$29:I$313,1,'Self-Assessment'!T$29:T$313,1),"") -> 0.625
A4: Public support & engagement | B4: =IFERROR(AVERAGEIFS('Self-Assessment'!D$29:D$313,'Self-Assessment'!J$29:J$313,1,'Self-Assessment'!N$29:N$313,1),"") -> 0.33333333 | C4: =IFERROR(AVERAGEIFS('Self-Assessment'!D$29:D$313,'Self-Assessment'!J$29:J$313,1,'Self-Assessment'!O$29:O$313,1),"") -> 0.75 | D4: =IFERROR(AVERAGEIFS('Self-Assessment'!D$29:D$313,'Self-Assessment'!J$29:J$313,1,'Self-Assessment'!P$29:P$313,1),"") -> 0.57142857 | E4: =IFERROR(AVERAGEIFS('Self-Assessment'!D$29:D$313,'Self-Assessment'!J$29:J$313,1,'Self-Assessment'!Q$29:Q$313,1),"") -> 0.6 | F4: =IFERROR(AVERAGEIFS('Self-Assessment'!D$29:D$313,'Self-Assessment'!J$29:J$313,1,'Self-Assessment'!R$29:R$313,1),"") -> 0.2 | G4: =IFERROR(AVERAGEIFS('Self-Assessment'!D$29:D$313,'Self-Assessment'!J$29:J$313,1,'Self-Assessment'!S$29:S$313,1),"") -> 0.6 | H4: =IFERROR(AVERAGEIFS('Self-Assessment'!D$29:D$313,'Self-Assessment'!J$29:J$313,1,'Self-Assessment'!T$29:T$313,1),"") -> 0.72222222
A5: Health & economic impact modelling | B5: =IFERROR(AVERAGEIFS('Self-Assessment'!D$29:D$313,'Self-Assessment'!K$29:K$313,1,'Self-Assessment'!N$29:N$313,1),"") -> 0.25 | C5: =IFERROR(AVERAGEIFS('Self-Assessment'!D$29:D$313,'Self-Assessment'!K$29:K$313,1,'Self-Assessment'!O$29:O$313,1),"") -> 0.17857143 | D5: =IFERROR(AVERAGEIFS('Self-Assessment'!D$29:D$313,'Self-Assessment'!K$29:K$313,1,'Self-Assessment'!P$29:P$313,1),"") -> 0.9 | E5: =IFERROR(AVERAGEIFS('Self-Assessment'!D$29:D$313,'Self-Assessment'!K$29:K$313,1,'Self-Assessment'!Q$29:Q$313,1),"") -> 0.66666667 | F5: =IFERROR(AVERAGEIFS('Self-Assessment'!D$29:D$313,'Self-Assessment'!K$29:K$313,1,'Self-Assessment'!R$29:R$313,1),"") -> 0.41176471 | G5: =IFERROR(AVERAGEIFS('Self-Assessment'!D$29:D$313,'Self-Assessment'!K$29:K$313,1,'Self-Assessment'!S$29:S$313,1),"") -> 0 | H5: =IFERROR(AVERAGEIFS('Self-Assessment'!D$29:D$313,'Self-Assessment'!K$29:K$313,1,'Self-Assessment'!T$29:T$313,1),"") -> 0.22222222
A6: Estimating air pollution | B6: =IFERROR(AVERAGEIFS('Self-Assessment'!D$29:D$313,'Self-Assessment'!L$29:L$313,1,'Self-Assessment'!N$29:N$313,1),"") -> 1.1666667 | C6: =IFERROR(AVERAGEIFS('Self-Assessment'!D$29:D$313,'Self-Assessment'!L$29:L$313,1,'Self-Assessment'!O$29:O$313,1),"") -> 0.83333333 | D6: =IFERROR(AVERAGEIFS('Self-Assessment'!D$29:D$313,'Self-Assessment'!L$29:L$313,1,'Self-Assessment'!P$29:P$313,1),"") -> 1 | E6: =IFERROR(AVERAGEIFS('Self-Assessment'!D$29:D$313,'Self-Assessment'!L$29:L$313,1,'Self-Assessment'!Q$29:Q$313,1),"") -> 1.2 | F6: =IFERROR(AVERAGEIFS('Self-Assessment'!D$29:D$313,'Self-Assessment'!L$29:L$313,1,'Self-Assessment'!R$29:R$313,1),"") -> 1.5416667 | G6: =IFERROR(AVERAGEIFS('Self-Assessment'!D$29:D$313,'Self-Assessment'!L$29:L$313,1,'Self-Assessment'!S$29:S$313,1),"") -> 0.75 | H6: =IFERROR(AVERAGEIFS('Self-Assessment'!D$29:D$313,'Self-Assessment'!L$29:L$313,1,'Self-Assessment'!T$29:T$313,1),"") -> 0.75
A7: Source & emission inventories | B7: =IFERROR(AVERAGEIFS('Self-Assessment'!D$29:D$313,'Self-Assessment'!M$29:M$313,1,'Self-Assessment'!N$29:N$313,1),"") -> 1.375 | C7: =IFERROR(AVERAGEIFS('Self-Assessment'!D$29:D$313,'Self-Assessment'!M$29:M$313,1,'Self-Assessment'!O$29:O$313,1),"") -> 0.78571429 | D7: =IFERROR(AVERAGEIFS('Self-Assessment'!D$29:D$313,'Self-Assessment'!M$29:M$313,1,'Self-Assessment'!P$29:P$313,1),"") -> 0.25 | E7: =IFERROR(AVERAGEIFS('Self-Assessment'!D$29:D$313,'Self-Assessment'!M$29:M$313,1,'Self-Assessment'!Q$29:Q$313,1),"") -> 1.75 | F7: =IFERROR(AVERAGEIFS('Self-Assessment'!D$29:D$313,'Self-Assessment'!M$29:M$313,1,'Self-Assessment'!R$29:R$313,1),"") -> 1 | G7: =IFERROR(AVERAGEIFS('Self-Assessment'!D$29:D$313,'Self-Assessment'!M$29:M$313,1,'Self-Assessment'!S$29:S$313,1),"") -> 1.9 | H7: =IFERROR(AVERAGEIFS('Self-Assessment'!D$29:D$313,'Self-Assessment'!M$29:M$313,1,'Self-Assessment'!T$29:T$313,1),"") -> 0.8
